Workbook

Sheet INÍCIO
B2: SISTEMA DE VENDAS & DASHBOARD GERENCIAL
B3: Painel Executivo de Vendas, Indicadores de Desempenho (KPIs) e Controle de Acesso
B5: SISTEMA ONLINE | OPERADOR ATIVO: ADMINISTRADOR (ADMIN)
B10: ?? FILTRO ATIVO: Período: [ Este Mês (outubro/2026) ] | Operador: [ Vitória ] | Pedidos no Filtro: [ 2 pedidos ]
B11: FATURAMENTO TOTAL | D11: VENDAS CONCLUÍDAS | G11: TICKET MÉDIO | I11: LÍQUIDO A RECEBER
B12: 706.83 | D12: 2 ped. (4 itens) | G12: 353.415 | I12: 689.33
B15: 🏆 TOP 5 MELHORES CLIENTES (VOLUME COMPRADO) | G15: ?? TOP 5 PRODUTOS & SERVIÇOS MAIS VENDIDOS
B16: Pos | C16: Cliente | D16: Vendas | E16: Total Gasto (R$) | G16: Pos | H16: Produto / Serviço | I16: Qtd | J16: Faturamento
B17: 1º | C17: Carlos Alberto da Silva | D17: 1 | E17: 500 | G17: 1º | H17: Teclado Mecânico ABNT2 | I17: 1 | J17: 350 | L17: Teclado Mecânico ABNT2 | M17: 350
B18: 2º | C18: Beatriz Souza Almeida | D18: 1 | E18: 206.83 | G18: 2º | H18: Mouse Gamer RGB | I18: 1 | J18: 150 | L18: Mouse Gamer RGB | M18: 150
B19: 3º | C19: - | D19: 0 | E19: 0 | G19: 3º | H19: Bola de pilates ventilado azul | I19: 1 | J19: 134.38 | L19: Bola de pilates ventilado azul | M19: 134.38
B20: 4º | C20: - | D20: 0 | E20: 0 | G20: 4º | H20: Bola de vôlei profissional verde | I20: 1 | J20: 72.45 | L20: Bola de vôlei profissional verde | M20: 72.45
B21: 5º | C21: - | D21: 0 | E21: 0 | G21: 5º | H21: - | I21: 0 | J21: 0 | L21: - | M21: 0
B23: 💳 FATURAMENTO POR FORMA DE PAGAMENTO
B24: Dinheiro | D24: 0
B25: PIX | D25: 206.83
B26: Cartão de Crédito | D26: 500
B27: Cartão de Débito | D27: 0
B28: Boleto Bancário | D28: 0
B30: Última atualização: 19/10/2026 19:14:52 | ?? Segurança Ativa: Acessos protegidos

Sheet APURACAO_RESULTADOS
B2: 📊 APURAÇÃO MENSAL DE RESULTADOS (DRE - DEMONSTRATIVO DO EXERCÍCIO)
B5: EMPRESA: | C5: =CONFIG!B2 | D5: ANO: | E5: 2026
B7: 💰 VENDAS BRUTAS (ANO) | D7: 📈 VENDAS LÍQUIDAS (ANO) | G7: 🏷️ LUCRO BRUTO (APÓS CMV) | J7: 💸 DESPESAS & CUSTOS | M7: 🏆 RESULTADO LÍQUIDO | P7: 📊 LUCRATIVIDADE (%)
B8: =P12 | D8: =P19 | G8: =P23 | J8: =P15+P20+P24+P30+P37+P46 | M8: =P49 | P8: =IFERROR(P49/P19,0)
B11: ITEM | C11: ESTRUTURA DE CONTAS (APURAÇÃO DE RESULTADOS) | D11: JAN | E11: FEV | F11: MAR | G11: ABR | H11: MAI | I11: JUN | J11: JUL | K11: AGO | L11: SET | M11: OUT | N11: NOV | O11: DEZ | P11: TOTAL ANUAL | Q11: A.V. (%)
B12: 1 | C12: VENDAS BRUTAS | D12: =SUM(D13:D14) | E12: =SUM(E13:E14) | F12: =SUM(F13:F14) | G12: =SUM(G13:G14) | H12: =SUM(H13:H14) | I12: =SUM(I13:I14) | J12: =SUM(J13:J14) | K12: =SUM(K13:K14) | ... O12: =SUM(O13:O14) | P12: =SUM(D12:O12) | Q12: =IFERROR(P12/$P$19, 0)
B13: 1.1 | C13: Vendas de produtos | D13: 0 | E13: 0 | F13: 0 | G13: 0 | H13: 0 | I13: 0 | J13: 0 | K13: 0 | L13: 0 | M13: 5234.8 | N13: 0 | O13: 0 | P13: =SUM(D13:O13) | Q13: =IFERROR(P13/$P$19, 0)
B14: 1.2 | C14: Prestação de serviços | D14: 0 | E14: 0 | F14: 0 | G14: 0 | H14: 0 | I14: 0 | J14: 0 | K14: 0 | L14: 0 | M14: 0 | N14: 0 | O14: 0 | P14: =SUM(D14:O14) | Q14: =IFERROR(P14/$P$19, 0)
B15: 2 | C15: (-) Deduções da Receita Bruta | D15: =SUM(D16:D18) | E15: =SUM(E16:E18) | F15: =SUM(F16:F18) | G15: =SUM(G16:G18) | H15: =SUM(H16:H18) | I15: =SUM(I16:I18) | J15: =SUM(J16:J18) | K15: =SUM(K16:K18) | ... O15: =SUM(O16:O18) | P15: =SUM(D15:O15) | Q15: =IFERROR(P15/$P$19, 0)
B16: 2.1 | C16: (-) Devoluções | D16: =SUMIFS(DESPESAS!$H:$H, DESPESAS!$E:$E, "2.1 (-) Devoluções", DESPESAS!$L:$L, 1, DESPESAS!$M:$M, $E$5, DESPESAS!$J:$J, "<>Cancelada") | E16: =SUMIFS(DESPESAS!$H:$H, DESPESAS!$E:$E, "2.1 (-) Devoluções", DESPESAS!$L:$L, 2, DESPESAS!$M:$M, $E$5, DESPESAS!$J:$J, "<>Cancelada") | F16: =SUMIFS(DESPESAS!$H:$H, DESPESAS!$E:$E, "2.1 (-) Devoluções", DESPESAS!$L:$L, 3, DESPESAS!$M:$M, $E$5, DESPESAS!$J:$J, "<>Cancelada") | G16: =SUMIFS(DESPESAS!$H:$H, DESPESAS!$E:$E, "2.1 (-) Devoluções", DESPESAS!$L:$L, 4, DESPESAS!$M:$M, $E$5, DESPESAS!$J:$J, "<>Cancelada") | H16: =SUMIFS(DESPESAS!$H:$H, DESPESAS!$E:$E, "2.1 (-) Devoluções", DESPESAS!$L:$L, 5, DESPESAS!$M:$M, $E$5, DESPESAS!$J:$J, "<>Cancelada") | I16: =SUMIFS(DESPESAS!$H:$H, DESPESAS!$E:$E, "2.1 (-) Devoluções", DESPESAS!$L:$L, 6, DESPESAS!$M:$M, $E$5, DESPESAS!$J:$J, "<>Cancelada") | J16: =SUMIFS(DESPESAS!$H:$H, DESPESAS!$E:$E, "2.1 (-) Devoluções", DESPESAS!$L:$L, 7, DESPESAS!$M:$M, $E$5, DESPESAS!$J:$J, "<>Cancelada") | K16: =SUMIFS(DESPESAS!$H:$H, DESPESAS!$E:$E, "2.1 (-) Devoluções", DESPESAS!$L:$L, 8, DESPESAS!$M:$M, $E$5, DESPESAS!$J:$J, "<>Cancelada") | L16: =SUMIFS(DESPESAS!$H:$H, DESPESAS!$E:$E, "2.1 (-) Devoluções", DESPESAS!$L:$L, 9, DESPESAS!$M:$M, $E$5, DESPESAS!$J:$J, "<>Cancelada") | M16: =SUMIFS(DESPESAS!$H:$H, DESPESAS!$E:$E, "2.1 (-) Devoluções", DESPESAS!$L:$L, 10, DESPESAS!$M:$M, $E$5, DESPESAS!$J:$J, "<>Cancelada") | N16: =SUMIFS(DESPESAS!$H:$H, DESPESAS!$E:$E, "2.1 (-) Devoluções", DESPESAS!$L:$L, 11, DESPESAS!$M:$M, $E$5, DESPESAS!$J:$J, "<>Cancelada") | O16: =SUMIFS(DESPESAS!$H:$H, DESPESAS!$E:$E, "2.1 (-) Devoluções", DESPESAS!$L:$L, 12, DESPESAS!$M:$M, $E$5, DESPESAS!$J:$J, "<>Cancelada") | P16: =SUM(D16:O16) | Q16: =IFERROR(P16/$P$19, 0)
B17: 2.2 | C17: (-) Impostos e Contribuições sobre vendas | D17: =SUMIFS(DESPESAS!$H:$H, DESPESAS!$E:$E, "2.2 (-) Impostos e Contribuições sobre vendas", DESPESAS!$L:$L, 1, DESPESAS!$M:$M, $E$5, DESPESAS!$J:$J, "<>Cancelada") | E17: =SUMIFS(DESPESAS!$H:$H, DESPESAS!$E:$E, "2.2 (-) Impostos e Contribuições sobre vendas", DESPESAS!$L:$L, 2, DESPESAS!$M:$M, $E$5, DESPESAS!$J:$J, "<>Cancelada") | F17: =SUMIFS(DESPESAS!$H:$H, DESPESAS!$E:$E, "2.2 (-) Impostos e Contribuições sobre vendas", DESPESAS!$L:$L, 3, DESPESAS!$M:$M, $E$5, DESPESAS!$J:$J, "<>Cancelada") | G17: =SUMIFS(DESPESAS!$H:$H, DESPESAS!$E:$E, "2.2 (-) Impostos e Contribuições sobre vendas", DESPESAS!$L:$L, 4, DESPESAS!$M:$M, $E$5, DESPESAS!$J:$J, "<>Cancelada") | H17: =SUMIFS(DESPESAS!$H:$H, DESPESAS!$E:$E, "2.2 (-) Impostos e Contribuições sobre vendas", DESPESAS!$L:$L, 5, DESPESAS!$M:$M, $E$5, DESPESAS!$J:$J, "<>Cancelada") | I17: =SUMIFS(DESPESAS!$H:$H, DESPESAS!$E:$E, "2.2 (-) Impostos e Contribuições sobre vendas", DESPESAS!$L:$L, 6, DESPESAS!$M:$M, $E$5, DESPESAS!$J:$J, "<>Cancelada") | J17: =SUMIFS(DESPESAS!$H:$H, DESPESAS!$E:$E, "2.2 (-) Impostos e Contribuições sobre vendas", DESPESAS!$L:$L, 7, DESPESAS!$M:$M, $E$5, DESPESAS!$J:$J, "<>Cancelada") | K17: =SUMIFS(DESPESAS!$H:$H, DESPESAS!$E:$E, "2.2 (-) Impostos e Contribuições sobre vendas", DESPESAS!$L:$L, 8, DESPESAS!$M:$M, $E$5, DESPESAS!$J:$J, "<>Cancelada") | L17: =SUMIFS(DESPESAS!$H:$H, DESPESAS!$E:$E, "2.2 (-) Impostos e Contribuições sobre vendas", DESPESAS!$L:$L, 9, DESPESAS!$M:$M, $E$5, DESPESAS!$J:$J, "<>Cancelada") | M17: =SUMIFS(DESPESAS!$H:$H, DESPESAS!$E:$E, "2.2 (-) Impostos e Contribuições sobre vendas", DESPESAS!$L:$L, 10, DESPESAS!$M:$M, $E$5, DESPESAS!$J:$J, "<>Cancelada") | N17: =SUMIFS(DESPESAS!$H:$H, DESPESAS!$E:$E, "2.2 (-) Impostos e Contribuições sobre vendas", DESPESAS!$L:$L, 11, DESPESAS!$M:$M, $E$5, DESPESAS!$J:$J, "<>Cancelada") | O17: =SUMIFS(DESPESAS!$H:$H, DESPESAS!$E:$E, "2.2 (-) Impostos e Contribuições sobre vendas", DESPESAS!$L:$L, 12, DESPESAS!$M:$M, $E$5, DESPESAS!$J:$J, "<>Cancelada") | P17: =SUM(D17:O17) | Q17: =IFERROR(P17/$P$19, 0)
B18: 2.3 | C18: (-) Abatimentos e Descontos Concedidos | D18: 0 | E18: 0 | F18: 0 | G18: 0 | H18: 0 | I18: 0 | J18: 0 | K18: 0 | L18: 0 | M18: 350 | N18: 0 | O18: 0 | P18: =SUM(D18:O18) | Q18: =IFERROR(P18/$P$19, 0)
B19: 3 | C19: Vendas Líquidas (1 - 2) | D19: =D12-D15 | E19: =E12-E15 | F19: =F12-F15 | G19: =G12-G15 | H19: =H12-H15 | I19: =I12-I15 | J19: =J12-J15 | K19: =K12-K15 | ... O19: =O12-O15 | P19: =SUM(D19:O19) | Q19: =IFERROR(P19/$P$19, 0)
B20: 4 | C20: Custos das Vendas (CMV / CSP) | D20: =SUM(D21:D22) | E20: =SUM(E21:E22) | F20: =SUM(F21:F22) | G20: =SUM(G21:G22) | H20: =SUM(H21:H22) | I20: =SUM(I21:I22) | J20: =SUM(J21:J22) | K20: =SUM(K21:K22) | ... O20: =SUM(O21:O22) | P20: =SUM(D20:O20) | Q20: =IFERROR(P20/$P$19, 0)
B21: 4.1 | C21: (-) Custo das Mercadorias Vendidas | D21: =0+SUMIFS(DESPESAS!$H:$H,DESPESAS!$E:$E,"4.1 (-) Custo das Mercadorias Vendidas",DESPESAS!$L:$L,1,DESPESAS!$M:$M,$E$5,DESPESAS!$J:$J,"<>Cancelada") | E21: =0+SUMIFS(DESPESAS!$H:$H,DESPESAS!$E:$E,"4.1 (-) Custo das Mercadorias Vendidas",DESPESAS!$L:$L,2,DESPESAS!$M:$M,$E$5,DESPESAS!$J:$J,"<>Cancelada") | F21: =0+SUMIFS(DESPESAS!$H:$H,DESPESAS!$E:$E,"4.1 (-) Custo das Mercadorias Vendidas",DESPESAS!$L:$L,3,DESPESAS!$M:$M,$E$5,DESPESAS!$J:$J,"<>Cancelada") | G21: =0+SUMIFS(DESPESAS!$H:$H,DESPESAS!$E:$E,"4.1 (-) Custo das Mercadorias Vendidas",DESPESAS!$L:$L,4,DESPESAS!$M:$M,$E$5,DESPESAS!$J:$J,"<>Cancelada") | H21: =0+SUMIFS(DESPESAS!$H:$H,DESPESAS!$E:$E,"4.1 (-) Custo das Mercadorias Vendidas",DESPESAS!$L:$L,5,DESPESAS!$M:$M,$E$5,DESPESAS!$J:$J,"<>Cancelada") | I21: =0+SUMIFS(DESPESAS!$H:$H,DESPESAS!$E:$E,"4.1 (-) Custo das Mercadorias Vendidas",DESPESAS!$L:$L,6,DESPESAS!$M:$M,$E$5,DESPESAS!$J:$J,"<>Cancelada") | J21: =0+SUMIFS(DESPESAS!$H:$H,DESPESAS!$E:$E,"4.1 (-) Custo das Mercadorias Vendidas",DESPESAS!$L:$L,7,DESPESAS!$M:$M,$E$5,DESPESAS!$J:$J,"<>Cancelada") | K21: =0+SUMIFS(DESPESAS!$H:$H,DESPESAS!$E:$E,"4.1 (-) Custo das Mercadorias Vendidas",DESPESAS!$L:$L,8,DESPESAS!$M:$M,$E$5,DESPESAS!$J:$J,"<>Cancelada") | L21: =0+SUMIFS(DESPESAS!$H:$H,DESPESAS!$E:$E,"4.1 (-) Custo das Mercadorias Vendidas",DESPESAS!$L:$L,9,DESPESAS!$M:$M,$E$5,DESPESAS!$J:$J,"<>Cancelada") | M21: =2674.86+SUMIFS(DESPESAS!$H:$H,DESPESAS!$E:$E,"4.1 (-) Custo das Mercadorias Vendidas",DESPESAS!$L:$L,10,DESPESAS!$M:$M,$E$5,DESPESAS!$J:$J,"<>Cancelada") | N21: =0+SUMIFS(DESPESAS!$H:$H,DESPESAS!$E:$E,"4.1 (-) Custo das Mercadorias Vendidas",DESPESAS!$L:$L,11,DESPESAS!$M:$M,$E$5,DESPESAS!$J:$J,"<>Cancelada") | O21: =0+SUMIFS(DESPESAS!$H:$H,DESPESAS!$E:$E,"4.1 (-) Custo das Mercadorias Vendidas",DESPESAS!$L:$L,12,DESPESAS!$M:$M,$E$5,DESPESAS!$J:$J,"<>Cancelada") | P21: =SUM(D21:O21) | Q21: =IFERROR(P21/$P$19, 0)
B22: 4.2 | C22: (-) Custo dos Serviços Prestados | D22: =0+SUMIFS(DESPESAS!$H:$H,DESPESAS!$E:$E,"4.2 (-) Custo dos Serviços Prestados",DESPESAS!$L:$L,1,DESPESAS!$M:$M,$E$5,DESPESAS!$J:$J,"<>Cancelada") | E22: =0+SUMIFS(DESPESAS!$H:$H,DESPESAS!$E:$E,"4.2 (-) Custo dos Serviços Prestados",DESPESAS!$L:$L,2,DESPESAS!$M:$M,$E$5,DESPESAS!$J:$J,"<>Cancelada") | F22: =0+SUMIFS(DESPESAS!$H:$H,DESPESAS!$E:$E,"4.2 (-) Custo dos Serviços Prestados",DESPESAS!$L:$L,3,DESPESAS!$M:$M,$E$5,DESPESAS!$J:$J,"<>Cancelada") | G22: =0+SUMIFS(DESPESAS!$H:$H,DESPESAS!$E:$E,"4.2 (-) Custo dos Serviços Prestados",DESPESAS!$L:$L,4,DESPESAS!$M:$M,$E$5,DESPESAS!$J:$J,"<>Cancelada") | H22: =0+SUMIFS(DESPESAS!$H:$H,DESPESAS!$E:$E,"4.2 (-) Custo dos Serviços Prestados",DESPESAS!$L:$L,5,DESPESAS!$M:$M,$E$5,DESPESAS!$J:$J,"<>Cancelada") | I22: =0+SUMIFS(DESPESAS!$H:$H,DESPESAS!$E:$E,"4.2 (-) Custo dos Serviços Prestados",DESPESAS!$L:$L,6,DESPESAS!$M:$M,$E$5,DESPESAS!$J:$J,"<>Cancelada") | J22: =0+SUMIFS(DESPESAS!$H:$H,DESPESAS!$E:$E,"4.2 (-) Custo dos Serviços Prestados",DESPESAS!$L:$L,7,DESPESAS!$M:$M,$E$5,DESPESAS!$J:$J,"<>Cancelada") | K22: =0+SUMIFS(DESPESAS!$H:$H,DESPESAS!$E:$E,"4.2 (-) Custo dos Serviços Prestados",DESPESAS!$L:$L,8,DESPESAS!$M:$M,$E$5,DESPESAS!$J:$J,"<>Cancelada") | L22: =0+SUMIFS(DESPESAS!$H:$H,DESPESAS!$E:$E,"4.2 (-) Custo dos Serviços Prestados",DESPESAS!$L:$L,9,DESPESAS!$M:$M,$E$5,DESPESAS!$J:$J,"<>Cancelada") | M22: =0+SUMIFS(DESPESAS!$H:$H,DESPESAS!$E:$E,"4.2 (-) Custo dos Serviços Prestados",DESPESAS!$L:$L,10,DESPESAS!$M:$M,$E$5,DESPESAS!$J:$J,"<>Cancelada") | N22: =0+SUMIFS(DESPESAS!$H:$H,DESPESAS!$E:$E,"4.2 (-) Custo dos Serviços Prestados",DESPESAS!$L:$L,11,DESPESAS!$M:$M,$E$5,DESPESAS!$J:$J,"<>Cancelada") | O22: =0+SUMIFS(DESPESAS!$H:$H,DESPESAS!$E:$E,"4.2 (-) Custo dos Serviços Prestados",DESPESAS!$L:$L,12,DESPESAS!$M:$M,$E$5,DESPESAS!$J:$J,"<>Cancelada") | P22: =SUM(D22:O22) | Q22: =IFERROR(P22/$P$19, 0)
B23: 5 | C23: Resultado Operacional Bruto (3 - 4) | D23: =D19-D20 | E23: =E19-E20 | F23: =F19-F20 | G23: =G19-G20 | H23: =H19-H20 | I23: =I19-I20 | J23: =J19-J20 | K23: =K19-K20 | ... O23: =O19-O20 | P23: =SUM(D23:O23) | Q23: =IFERROR(P23/$P$19, 0)
B24: 6 | C24: Despesas Operacionais | D24: =SUM(D25:D26) | E24: =SUM(E25:E26) | F24: =SUM(F25:F26) | G24: =SUM(G25:G26) | H24: =SUM(H25:H26) | I24: =SUM(I25:I26) | J24: =SUM(J25:J26) | K24: =SUM(K25:K26) | ... O24: =SUM(O25:O26) | P24: =SUM(D24:O24) | Q24: =IFERROR(P24/$P$19, 0)
B25: 6.1 | C25: Despesas com Vendas | D25: =SUMIFS(DESPESAS!$H:$H, DESPESAS!$E:$E, "6.1 Despesas com Vendas", DESPESAS!$L:$L, 1, DESPESAS!$M:$M, $E$5, DESPESAS!$J:$J, "<>Cancelada") | E25: =SUMIFS(DESPESAS!$H:$H, DESPESAS!$E:$E, "6.1 Despesas com Vendas", DESPESAS!$L:$L, 2, DESPESAS!$M:$M, $E$5, DESPESAS!$J:$J, "<>Cancelada") | F25: =SUMIFS(DESPESAS!$H:$H, DESPESAS!$E:$E, "6.1 Despesas com Vendas", DESPESAS!$L:$L, 3, DESPESAS!$M:$M, $E$5, DESPESAS!$J:$J, "<>Cancelada") | G25: =SUMIFS(DESPESAS!$H:$H, DESPESAS!$E:$E, "6.1 Despesas com Vendas", DESPESAS!$L:$L, 4, DESPESAS!$M:$M, $E$5, DESPESAS!$J:$J, "<>Cancelada") | H25: =SUMIFS(DESPESAS!$H:$H, DESPESAS!$E:$E, "6.1 Despesas com Vendas", DESPESAS!$L:$L, 5, DESPESAS!$M:$M, $E$5, DESPESAS!$J:$J, "<>Cancelada") | I25: =SUMIFS(DESPESAS!$H:$H, DESPESAS!$E:$E, "6.1 Despesas com Vendas", DESPESAS!$L:$L, 6, DESPESAS!$M:$M, $E$5, DESPESAS!$J:$J, "<>Cancelada") | J25: =SUMIFS(DESPESAS!$H:$H, DESPESAS!$E:$E, "6.1 Despesas com Vendas", DESPESAS!$L:$L, 7, DESPESAS!$M:$M, $E$5, DESPESAS!$J:$J, "<>Cancelada") | K25: =SUMIFS(DESPESAS!$H:$H, DESPESAS!$E:$E, "6.1 Despesas com Vendas", DESPESAS!$L:$L, 8, DESPESAS!$M:$M, $E$5, DESPESAS!$J:$J, "<>Cancelada") | L25: =SUMIFS(DESPESAS!$H:$H, DESPESAS!$E:$E, "6.1 Despesas com Vendas", DESPESAS!$L:$L, 9, DESPESAS!$M:$M, $E$5, DESPESAS!$J:$J, "<>Cancelada") | M25: =SUMIFS(DESPESAS!$H:$H, DESPESAS!$E:$E, "6.1 Despesas com Vendas", DESPESAS!$L:$L, 10, DESPESAS!$M:$M, $E$5, DESPESAS!$J:$J, "<>Cancelada") | N25: =SUMIFS(DESPESAS!$H:$H, DESPESAS!$E:$E, "6.1 Despesas com Vendas", DESPESAS!$L:$L, 11, DESPESAS!$M:$M, $E$5, DESPESAS!$J:$J, "<>Cancelada") | O25: =SUMIFS(DESPESAS!$H:$H, DESPESAS!$E:$E, "6.1 Despesas com Vendas", DESPESAS!$L:$L, 12, DESPESAS!$M:$M, $E$5, DESPESAS!$J:$J, "<>Cancelada") | P25: =SUM(D25:O25) | Q25: =IFERROR(P25/$P$19, 0)
B26: 6.2 | C26: Despesas Administrativas (água, luz, telefone, aluguel, folha, etc.) | D26: =SUMIFS(DESPESAS!$H:$H, DESPESAS!$E:$E, "6.2 Despesas Administrativas", DESPESAS!$L:$L, 1, DESPESAS!$M:$M, $E$5, DESPESAS!$J:$J, "<>Cancelada") | E26: =SUMIFS(DESPESAS!$H:$H, DESPESAS!$E:$E, "6.2 Despesas Administrativas", DESPESAS!$L:$L, 2, DESPESAS!$M:$M, $E$5, DESPESAS!$J:$J, "<>Cancelada") | F26: =SUMIFS(DESPESAS!$H:$H, DESPESAS!$E:$E, "6.2 Despesas Administrativas", DESPESAS!$L:$L, 3, DESPESAS!$M:$M, $E$5, DESPESAS!$J:$J, "<>Cancelada") | G26: =SUMIFS(DESPESAS!$H:$H, DESPESAS!$E:$E, "6.2 Despesas Administrativas", DESPESAS!$L:$L, 4, DESPESAS!$M:$M, $E$5, DESPESAS!$J:$J, "<>Cancelada") | H26: =SUMIFS(DESPESAS!$H:$H, DESPESAS!$E:$E, "6.2 Despesas Administrativas", DESPESAS!$L:$L, 5, DESPESAS!$M:$M, $E$5, DESPESAS!$J:$J, "<>Cancelada") | I26: =SUMIFS(DESPESAS!$H:$H, DESPESAS!$E:$E, "6.2 Despesas Administrativas", DESPESAS!$L:$L, 6, DESPESAS!$M:$M, $E$5, DESPESAS!$J:$J, "<>Cancelada") | J26: =SUMIFS(DESPESAS!$H:$H, DESPESAS!$E:$E, "6.2 Despesas Administrativas", DESPESAS!$L:$L, 7, DESPESAS!$M:$M, $E$5, DESPESAS!$J:$J, "<>Cancelada") | K26: =SUMIFS(DESPESAS!$H:$H, DESPESAS!$E:$E, "6.2 Despesas Administrativas", DESPESAS!$L:$L, 8, DESPESAS!$M:$M, $E$5, DESPESAS!$J:$J, "<>Cancelada") | L26: =SUMIFS(DESPESAS!$H:$H, DESPESAS!$E:$E, "6.2 Despesas Administrativas", DESPESAS!$L:$L, 9, DESPESAS!$M:$M, $E$5, DESPESAS!$J:$J, "<>Cancelada") | M26: =SUMIFS(DESPESAS!$H:$H, DESPESAS!$E:$E, "6.2 Despesas Administrativas", DESPESAS!$L:$L, 10, DESPESAS!$M:$M, $E$5, DESPESAS!$J:$J, "<>Cancelada") | N26: =SUMIFS(DESPESAS!$H:$H, DESPESAS!$E:$E, "6.2 Despesas Administrativas", DESPESAS!$L:$L, 11, DESPESAS!$M:$M, $E$5, DESPESAS!$J:$J, "<>Cancelada") | O26: =SUMIFS(DESPESAS!$H:$H, DESPESAS!$E:$E, "6.2 Despesas Administrativas", DESPESAS!$L:$L, 12, DESPESAS!$M:$M, $E$5, DESPESAS!$J:$J, "<>Cancelada") | P26: =SUM(D26:O26) | Q26: =IFERROR(P26/$P$19, 0)
B27: 7 | C27: Receitas Financeiras Líquidas | D27: =SUM(D28:D29) | E27: =SUM(E28:E29) | F27: =SUM(F28:F29) | G27: =SUM(G28:G29) | H27: =SUM(H28:H29) | I27: =SUM(I28:I29) | J27: =SUM(J28:J29) | K27: =SUM(K28:K29) | ... O27: =SUM(O28:O29) | P27: =SUM(D27:O27) | Q27: =IFERROR(P27/$P$19, 0)
B28: 7.1 | C28: Receitas Financeiras | D28: =SUMIFS(DESPESAS!$H:$H, DESPESAS!$E:$E, "7.1 Receitas Financeiras", DESPESAS!$L:$L, 1, DESPESAS!$M:$M, $E$5, DESPESAS!$J:$J, "<>Cancelada") | E28: =SUMIFS(DESPESAS!$H:$H, DESPESAS!$E:$E, "7.1 Receitas Financeiras", DESPESAS!$L:$L, 2, DESPESAS!$M:$M, $E$5, DESPESAS!$J:$J, "<>Cancelada") | F28: =SUMIFS(DESPESAS!$H:$H, DESPESAS!$E:$E, "7.1 Receitas Financeiras", DESPESAS!$L:$L, 3, DESPESAS!$M:$M, $E$5, DESPESAS!$J:$J, "<>Cancelada") | G28: =SUMIFS(DESPESAS!$H:$H, DESPESAS!$E:$E, "7.1 Receitas Financeiras", DESPESAS!$L:$L, 4, DESPESAS!$M:$M, $E$5, DESPESAS!$J:$J, "<>Cancelada") | H28: =SUMIFS(DESPESAS!$H:$H, DESPESAS!$E:$E, "7.1 Receitas Financeiras", DESPESAS!$L:$L, 5, DESPESAS!$M:$M, $E$5, DESPESAS!$J:$J, "<>Cancelada") | I28: =SUMIFS(DESPESAS!$H:$H, DESPESAS!$E:$E, "7.1 Receitas Financeiras", DESPESAS!$L:$L, 6, DESPESAS!$M:$M, $E$5, DESPESAS!$J:$J, "<>Cancelada") | J28: =SUMIFS(DESPESAS!$H:$H, DESPESAS!$E:$E, "7.1 Receitas Financeiras", DESPESAS!$L:$L, 7, DESPESAS!$M:$M, $E$5, DESPESAS!$J:$J, "<>Cancelada") | K28: =SUMIFS(DESPESAS!$H:$H, DESPESAS!$E:$E, "7.1 Receitas Financeiras", DESPESAS!$L:$L, 8, DESPESAS!$M:$M, $E$5, DESPESAS!$J:$J, "<>Cancelada") | L28: =SUMIFS(DESPESAS!$H:$H, DESPESAS!$E:$E, "7.1 Receitas Financeiras", DESPESAS!$L:$L, 9, DESPESAS!$M:$M, $E$5, DESPESAS!$J:$J, "<>Cancelada") | M28: =SUMIFS(DESPESAS!$H:$H, DESPESAS!$E:$E, "7.1 Receitas Financeiras", DESPESAS!$L:$L, 10, DESPESAS!$M:$M, $E$5, DESPESAS!$J:$J, "<>Cancelada") | N28: =SUMIFS(DESPESAS!$H:$H, DESPESAS!$E:$E, "7.1 Receitas Financeiras", DESPESAS!$L:$L, 11, DESPESAS!$M:$M, $E$5, DESPESAS!$J:$J, "<>Cancelada") | O28: =SUMIFS(DESPESAS!$H:$H, DESPESAS!$E:$E, "7.1 Receitas Financeiras", DESPESAS!$L:$L, 12, DESPESAS!$M:$M, $E$5, DESPESAS!$J:$J, "<>Cancelada") | P28: =SUM(D28:O28) | Q28: =IFERROR(P28/$P$19, 0)
B29: 7.2 | C29: Variações Monetárias e Cambiais Ativas | D29: =SUMIFS(DESPESAS!$H:$H, DESPESAS!$E:$E, "7.2 Variações Monetárias e Cambiais Ativas", DESPESAS!$L:$L, 1, DESPESAS!$M:$M, $E$5, DESPESAS!$J:$J, "<>Cancelada") | E29: =SUMIFS(DESPESAS!$H:$H, DESPESAS!$E:$E, "7.2 Variações Monetárias e Cambiais Ativas", DESPESAS!$L:$L, 2, DESPESAS!$M:$M, $E$5, DESPESAS!$J:$J, "<>Cancelada") | F29: =SUMIFS(DESPESAS!$H:$H, DESPESAS!$E:$E, "7.2 Variações Monetárias e Cambiais Ativas", DESPESAS!$L:$L, 3, DESPESAS!$M:$M, $E$5, DESPESAS!$J:$J, "<>Cancelada") | G29: =SUMIFS(DESPESAS!$H:$H, DESPESAS!$E:$E, "7.2 Variações Monetárias e Cambiais Ativas", DESPESAS!$L:$L, 4, DESPESAS!$M:$M, $E$5, DESPESAS!$J:$J, "<>Cancelada") | H29: =SUMIFS(DESPESAS!$H:$H, DESPESAS!$E:$E, "7.2 Variações Monetárias e Cambiais Ativas", DESPESAS!$L:$L, 5, DESPESAS!$M:$M, $E$5, DESPESAS!$J:$J, "<>Cancelada") | I29: =SUMIFS(DESPESAS!$H:$H, DESPESAS!$E:$E, "7.2 Variações Monetárias e Cambiais Ativas", DESPESAS!$L:$L, 6, DESPESAS!$M:$M, $E$5, DESPESAS!$J:$J, "<>Cancelada") | J29: =SUMIFS(DESPESAS!$H:$H, DESPESAS!$E:$E, "7.2 Variações Monetárias e Cambiais Ativas", DESPESAS!$L:$L, 7, DESPESAS!$M:$M, $E$5, DESPESAS!$J:$J, "<>Cancelada") | K29: =SUMIFS(DESPESAS!$H:$H, DESPESAS!$E:$E, "7.2 Variações Monetárias e Cambiais Ativas", DESPESAS!$L:$L, 8, DESPESAS!$M:$M, $E$5, DESPESAS!$J:$J, "<>Cancelada") | L29: =SUMIFS(DESPESAS!$H:$H, DESPESAS!$E:$E, "7.2 Variações Monetárias e Cambiais Ativas", DESPESAS!$L:$L, 9, DESPESAS!$M:$M, $E$5, DESPESAS!$J:$J, "<>Cancelada") | M29: =SUMIFS(DESPESAS!$H:$H, DESPESAS!$E:$E, "7.2 Variações Monetárias e Cambiais Ativas", DESPESAS!$L:$L, 10, DESPESAS!$M:$M, $E$5, DESPESAS!$J:$J, "<>Cancelada") | N29: =SUMIFS(DESPESAS!$H:$H, DESPESAS!$E:$E, "7.2 Variações Monetárias e Cambiais Ativas", DESPESAS!$L:$L, 11, DESPESAS!$M:$M, $E$5, DESPESAS!$J:$J, "<>Cancelada") | O29: =SUMIFS(DESPESAS!$H:$H, DESPESAS!$E:$E, "7.2 Variações Monetárias e Cambiais Ativas", DESPESAS!$L:$L, 12, DESPESAS!$M:$M, $E$5, DESPESAS!$J:$J, "<>Cancelada") | P29: =SUM(D29:O29) | Q29: =IFERROR(P29/$P$19, 0)
B30: 8 | C30: Despesas Financeiras Líquidas | D30: =SUM(D31:D32) | E30: =SUM(E31:E32) | F30: =SUM(F31:F32) | G30: =SUM(G31:G32) | H30: =SUM(H31:H32) | I30: =SUM(I31:I32) | J30: =SUM(J31:J32) | K30: =SUM(K31:K32) | ... O30: =SUM(O31:O32) | P30: =SUM(D30:O30) | Q30: =IFERROR(P30/$P$19, 0)
B31: 8.1 | C31: Despesas Financeiras (Taxas Cartão PDV, Juros e Tarifas Bancos) | D31: =0+SUMIFS(DESPESAS!$H:$H,DESPESAS!$E:$E,"8.1 Despesas Financeiras",DESPESAS!$L:$L,1,DESPESAS!$M:$M,$E$5,DESPESAS!$J:$J,"<>Cancelada") | E31: =0+SUMIFS(DESPESAS!$H:$H,DESPESAS!$E:$E,"8.1 Despesas Financeiras",DESPESAS!$L:$L,2,DESPESAS!$M:$M,$E$5,DESPESAS!$J:$J,"<>Cancelada") | F31: =0+SUMIFS(DESPESAS!$H:$H,DESPESAS!$E:$E,"8.1 Despesas Financeiras",DESPESAS!$L:$L,3,DESPESAS!$M:$M,$E$5,DESPESAS!$J:$J,"<>Cancelada") | G31: =0+SUMIFS(DESPESAS!$H:$H,DESPESAS!$E:$E,"8.1 Despesas Financeiras",DESPESAS!$L:$L,4,DESPESAS!$M:$M,$E$5,DESPESAS!$J:$J,"<>Cancelada") | H31: =0+SUMIFS(DESPESAS!$H:$H,DESPESAS!$E:$E,"8.1 Despesas Financeiras",DESPESAS!$L:$L,5,DESPESAS!$M:$M,$E$5,DESPESAS!$J:$J,"<>Cancelada") | I31: =0+SUMIFS(DESPESAS!$H:$H,DESPESAS!$E:$E,"8.1 Despesas Financeiras",DESPESAS!$L:$L,6,DESPESAS!$M:$M,$E$5,DESPESAS!$J:$J,"<>Cancelada") | J31: =0+SUMIFS(DESPESAS!$H:$H,DESPESAS!$E:$E,"8.1 Despesas Financeiras",DESPESAS!$L:$L,7,DESPESAS!$M:$M,$E$5,DESPESAS!$J:$J,"<>Cancelada") | K31: =0+SUMIFS(DESPESAS!$H:$H,DESPESAS!$E:$E,"8.1 Despesas Financeiras",DESPESAS!$L:$L,8,DESPESAS!$M:$M,$E$5,DESPESAS!$J:$J,"<>Cancelada") | L31: =0+SUMIFS(DESPESAS!$H:$H,DESPESAS!$E:$E,"8.1 Despesas Financeiras",DESPESAS!$L:$L,9,DESPESAS!$M:$M,$E$5,DESPESAS!$J:$J,"<>Cancelada") | M31: =146.19+SUMIFS(DESPESAS!$H:$H,DESPESAS!$E:$E,"8.1 Despesas Financeiras",DESPESAS!$L:$L,10,DESPESAS!$M:$M,$E$5,DESPESAS!$J:$J,"<>Cancelada") | N31: =0+SUMIFS(DESPESAS!$H:$H,DESPESAS!$E:$E,"8.1 Despesas Financeiras",DESPESAS!$L:$L,11,DESPESAS!$M:$M,$E$5,DESPESAS!$J:$J,"<>Cancelada") | O31: =0+SUMIFS(DESPESAS!$H:$H,DESPESAS!$E:$E,"8.1 Despesas Financeiras",DESPESAS!$L:$L,12,DESPESAS!$M:$M,$E$5,DESPESAS!$J:$J,"<>Cancelada") | P31: =SUM(D31:O31) | Q31: =IFERROR(P31/$P$19, 0)
B32: 8.2 | C32: Variações Monetárias e Cambiais Passivas | D32: =SUMIFS(DESPESAS!$H:$H, DESPESAS!$E:$E, "8.2 Variações Monetárias e Cambiais Passivas", DESPESAS!$L:$L, 1, DESPESAS!$M:$M, $E$5, DESPESAS!$J:$J, "<>Cancelada") | E32: =SUMIFS(DESPESAS!$H:$H, DESPESAS!$E:$E, "8.2 Variações Monetárias e Cambiais Passivas", DESPESAS!$L:$L, 2, DESPESAS!$M:$M, $E$5, DESPESAS!$J:$J, "<>Cancelada") | F32: =SUMIFS(DESPESAS!$H:$H, DESPESAS!$E:$E, "8.2 Variações Monetárias e Cambiais Passivas", DESPESAS!$L:$L, 3, DESPESAS!$M:$M, $E$5, DESPESAS!$J:$J, "<>Cancelada") | G32: =SUMIFS(DESPESAS!$H:$H, DESPESAS!$E:$E, "8.2 Variações Monetárias e Cambiais Passivas", DESPESAS!$L:$L, 4, DESPESAS!$M:$M, $E$5, DESPESAS!$J:$J, "<>Cancelada") | H32: =SUMIFS(DESPESAS!$H:$H, DESPESAS!$E:$E, "8.2 Variações Monetárias e Cambiais Passivas", DESPESAS!$L:$L, 5, DESPESAS!$M:$M, $E$5, DESPESAS!$J:$J, "<>Cancelada") | I32: =SUMIFS(DESPESAS!$H:$H, DESPESAS!$E:$E, "8.2 Variações Monetárias e Cambiais Passivas", DESPESAS!$L:$L, 6, DESPESAS!$M:$M, $E$5, DESPESAS!$J:$J, "<>Cancelada") | J32: =SUMIFS(DESPESAS!$H:$H, DESPESAS!$E:$E, "8.2 Variações Monetárias e Cambiais Passivas", DESPESAS!$L:$L, 7, DESPESAS!$M:$M, $E$5, DESPESAS!$J:$J, "<>Cancelada") | K32: =SUMIFS(DESPESAS!$H:$H, DESPESAS!$E:$E, "8.2 Variações Monetárias e Cambiais Passivas", DESPESAS!$L:$L, 8, DESPESAS!$M:$M, $E$5, DESPESAS!$J:$J, "<>Cancelada") | L32: =SUMIFS(DESPESAS!$H:$H, DESPESAS!$E:$E, "8.2 Variações Monetárias e Cambiais Passivas", DESPESAS!$L:$L, 9, DESPESAS!$M:$M, $E$5, DESPESAS!$J:$J, "<>Cancelada") | M32: =SUMIFS(DESPESAS!$H:$H, DESPESAS!$E:$E, "8.2 Variações Monetárias e Cambiais Passivas", DESPESAS!$L:$L, 10, DESPESAS!$M:$M, $E$5, DESPESAS!$J:$J, "<>Cancelada") | N32: =SUMIFS(DESPESAS!$H:$H, DESPESAS!$E:$E, "8.2 Variações Monetárias e Cambiais Passivas", DESPESAS!$L:$L, 11, DESPESAS!$M:$M, $E$5, DESPESAS!$J:$J, "<>Cancelada") | O32: =SUMIFS(DESPESAS!$H:$H, DESPESAS!$E:$E, "8.2 Variações Monetárias e Cambiais Passivas", DESPESAS!$L:$L, 12, DESPESAS!$M:$M, $E$5, DESPESAS!$J:$J, "<>Cancelada") | P32: =SUM(D32:O32) | Q32: =IFERROR(P32/$P$19, 0)
B33: 9 | C33: Resultado Financeiro Líquido (7 - 8) | D33: =D27-D30 | E33: =E27-E30 | F33: =F27-F30 | G33: =G27-G30 | H33: =H27-H30 | I33: =I27-I30 | J33: =J27-J30 | K33: =K27-K30 | ... O33: =O27-O30 | P33: =SUM(D33:O33) | Q33: =IFERROR(P33/$P$19, 0)
B34: 10 | C34: Outras Receitas | D34: =SUM(D35:D36) | E34: =SUM(E35:E36) | F34: =SUM(F35:F36) | G34: =SUM(G35:G36) | H34: =SUM(H35:H36) | I34: =SUM(I35:I36) | J34: =SUM(J35:J36) | K34: =SUM(K35:K36) | ... O34: =SUM(O35:O36) | P34: =SUM(D34:O34) | Q34: =IFERROR(P34/$P$19, 0)
B35: 10.1 | C35: Resultado de Equivalência Patrimonial | D35: =SUMIFS(DESPESAS!$H:$H, DESPESAS!$E:$E, "10.1 Resultado de Equivalência Patrimonial", DESPESAS!$L:$L, 1, DESPESAS!$M:$M, $E$5, DESPESAS!$J:$J, "<>Cancelada") | E35: =SUMIFS(DESPESAS!$H:$H, DESPESAS!$E:$E, "10.1 Resultado de Equivalência Patrimonial", DESPESAS!$L:$L, 2, DESPESAS!$M:$M, $E$5, DESPESAS!$J:$J, "<>Cancelada") | F35: =SUMIFS(DESPESAS!$H:$H, DESPESAS!$E:$E, "10.1 Resultado de Equivalência Patrimonial", DESPESAS!$L:$L, 3, DESPESAS!$M:$M, $E$5, DESPESAS!$J:$J, "<>Cancelada") | G35: =SUMIFS(DESPESAS!$H:$H, DESPESAS!$E:$E, "10.1 Resultado de Equivalência Patrimonial", DESPESAS!$L:$L, 4, DESPESAS!$M:$M, $E$5, DESPESAS!$J:$J, "<>Cancelada") | H35: =SUMIFS(DESPESAS!$H:$H, DESPESAS!$E:$E, "10.1 Resultado de Equivalência Patrimonial", DESPESAS!$L:$L, 5, DESPESAS!$M:$M, $E$5, DESPESAS!$J:$J, "<>Cancelada") | I35: =SUMIFS(DESPESAS!$H:$H, DESPESAS!$E:$E, "10.1 Resultado de Equivalência Patrimonial", DESPESAS!$L:$L, 6, DESPESAS!$M:$M, $E$5, DESPESAS!$J:$J, "<>Cancelada") | J35: =SUMIFS(DESPESAS!$H:$H, DESPESAS!$E:$E, "10.1 Resultado de Equivalência Patrimonial", DESPESAS!$L:$L, 7, DESPESAS!$M:$M, $E$5, DESPESAS!$J:$J, "<>Cancelada") | K35: =SUMIFS(DESPESAS!$H:$H, DESPESAS!$E:$E, "10.1 Resultado de Equivalência Patrimonial", DESPESAS!$L:$L, 8, DESPESAS!$M:$M, $E$5, DESPESAS!$J:$J, "<>Cancelada") | L35: =SUMIFS(DESPESAS!$H:$H, DESPESAS!$E:$E, "10.1 Resultado de Equivalência Patrimonial", DESPESAS!$L:$L, 9, DESPESAS!$M:$M, $E$5, DESPESAS!$J:$J, "<>Cancelada") | M35: =SUMIFS(DESPESAS!$H:$H, DESPESAS!$E:$E, "10.1 Resultado de Equivalência Patrimonial", DESPESAS!$L:$L, 10, DESPESAS!$M:$M, $E$5, DESPESAS!$J:$J, "<>Cancelada") | N35: =SUMIFS(DESPESAS!$H:$H, DESPESAS!$E:$E, "10.1 Resultado de Equivalência Patrimonial", DESPESAS!$L:$L, 11, DESPESAS!$M:$M, $E$5, DESPESAS!$J:$J, "<>Cancelada") | O35: =SUMIFS(DESPESAS!$H:$H, DESPESAS!$E:$E, "10.1 Resultado de Equivalência Patrimonial", DESPESAS!$L:$L, 12, DESPESAS!$M:$M, $E$5, DESPESAS!$J:$J, "<>Cancelada") | P35: =SUM(D35:O35) | Q35: =IFERROR(P35/$P$19, 0)
B36: 10.2 | C36: Venda de Bens e Direitos do Ativo Não Circulante | D36: =SUMIFS(DESPESAS!$H:$H, DESPESAS!$E:$E, "10.2 Venda de Bens e Direitos do Ativo Não Circulante", DESPESAS!$L:$L, 1, DESPESAS!$M:$M, $E$5, DESPESAS!$J:$J, "<>Cancelada") | E36: =SUMIFS(DESPESAS!$H:$H, DESPESAS!$E:$E, "10.2 Venda de Bens e Direitos do Ativo Não Circulante", DESPESAS!$L:$L, 2, DESPESAS!$M:$M, $E$5, DESPESAS!$J:$J, "<>Cancelada") | F36: =SUMIFS(DESPESAS!$H:$H, DESPESAS!$E:$E, "10.2 Venda de Bens e Direitos do Ativo Não Circulante", DESPESAS!$L:$L, 3, DESPESAS!$M:$M, $E$5, DESPESAS!$J:$J, "<>Cancelada") | G36: =SUMIFS(DESPESAS!$H:$H, DESPESAS!$E:$E, "10.2 Venda de Bens e Direitos do Ativo Não Circulante", DESPESAS!$L:$L, 4, DESPESAS!$M:$M, $E$5, DESPESAS!$J:$J, "<>Cancelada") | H36: =SUMIFS(DESPESAS!$H:$H, DESPESAS!$E:$E, "10.2 Venda de Bens e Direitos do Ativo Não Circulante", DESPESAS!$L:$L, 5, DESPESAS!$M:$M, $E$5, DESPESAS!$J:$J, "<>Cancelada") | I36: =SUMIFS(DESPESAS!$H:$H, DESPESAS!$E:$E, "10.2 Venda de Bens e Direitos do Ativo Não Circulante", DESPESAS!$L:$L, 6, DESPESAS!$M:$M, $E$5, DESPESAS!$J:$J, "<>Cancelada") | J36: =SUMIFS(DESPESAS!$H:$H, DESPESAS!$E:$E, "10.2 Venda de Bens e Direitos do Ativo Não Circulante", DESPESAS!$L:$L, 7, DESPESAS!$M:$M, $E$5, DESPESAS!$J:$J, "<>Cancelada") | K36: =SUMIFS(DESPESAS!$H:$H, DESPESAS!$E:$E, "10.2 Venda de Bens e Direitos do Ativo Não Circulante", DESPESAS!$L:$L, 8, DESPESAS!$M:$M, $E$5, DESPESAS!$J:$J, "<>Cancelada") | L36: =SUMIFS(DESPESAS!$H:$H, DESPESAS!$E:$E, "10.2 Venda de Bens e Direitos do Ativo Não Circulante", DESPESAS!$L:$L, 9, DESPESAS!$M:$M, $E$5, DESPESAS!$J:$J, "<>Cancelada") | M36: =SUMIFS(DESPESAS!$H:$H, DESPESAS!$E:$E, "10.2 Venda de Bens e Direitos do Ativo Não Circulante", DESPESAS!$L:$L, 10, DESPESAS!$M:$M, $E$5, DESPESAS!$J:$J, "<>Cancelada") | N36: =SUMIFS(DESPESAS!$H:$H, DESPESAS!$E:$E, "10.2 Venda de Bens e Direitos do Ativo Não Circulante", DESPESAS!$L:$L, 11, DESPESAS!$M:$M, $E$5, DESPESAS!$J:$J, "<>Cancelada") | O36: =SUMIFS(DESPESAS!$H:$H, DESPESAS!$E:$E, "10.2 Venda de Bens e Direitos do Ativo Não Circulante", DESPESAS!$L:$L, 12, DESPESAS!$M:$M, $E$5, DESPESAS!$J:$J, "<>Cancelada") | P36: =SUM(D36:O36) | Q36: =IFERROR(P36/$P$19, 0)
B37: 11 | C37: Outras Despesas | D37: =SUM(D38:D44) | E37: =SUM(E38:E44) | F37: =SUM(F38:F44) | G37: =SUM(G38:G44) | H37: =SUM(H38:H44) | I37: =SUM(I38:I44) | J37: =SUM(J38:J44) | K37: =SUM(K38:K44) | ... O37: =SUM(O38:O44) | P37: =SUM(D37:O37) | Q37: =IFERROR(P37/$P$19, 0)
B38: 11.1 | C38: Serviços de contabilidade | D38: =SUMIFS(DESPESAS!$H:$H, DESPESAS!$E:$E, "11.1 Serviços de contabilidade", DESPESAS!$L:$L, 1, DESPESAS!$M:$M, $E$5, DESPESAS!$J:$J, "<>Cancelada") | E38: =SUMIFS(DESPESAS!$H:$H, DESPESAS!$E:$E, "11.1 Serviços de contabilidade", DESPESAS!$L:$L, 2, DESPESAS!$M:$M, $E$5, DESPESAS!$J:$J, "<>Cancelada") | F38: =SUMIFS(DESPESAS!$H:$H, DESPESAS!$E:$E, "11.1 Serviços de contabilidade", DESPESAS!$L:$L, 3, DESPESAS!$M:$M, $E$5, DESPESAS!$J:$J, "<>Cancelada") | G38: =SUMIFS(DESPESAS!$H:$H, DESPESAS!$E:$E, "11.1 Serviços de contabilidade", DESPESAS!$L:$L, 4, DESPESAS!$M:$M, $E$5, DESPESAS!$J:$J, "<>Cancelada") | H38: =SUMIFS(DESPESAS!$H:$H, DESPESAS!$E:$E, "11.1 Serviços de contabilidade", DESPESAS!$L:$L, 5, DESPESAS!$M:$M, $E$5, DESPESAS!$J:$J, "<>Cancelada") | I38: =SUMIFS(DESPESAS!$H:$H, DESPESAS!$E:$E, "11.1 Serviços de contabilidade", DESPESAS!$L:$L, 6, DESPESAS!$M:$M, $E$5, DESPESAS!$J:$J, "<>Cancelada") | J38: =SUMIFS(DESPESAS!$H:$H, DESPESAS!$E:$E, "11.1 Serviços de contabilidade", DESPESAS!$L:$L, 7, DESPESAS!$M:$M, $E$5, DESPESAS!$J:$J, "<>Cancelada") | K38: =SUMIFS(DESPESAS!$H:$H, DESPESAS!$E:$E, "11.1 Serviços de contabilidade", DESPESAS!$L:$L, 8, DESPESAS!$M:$M, $E$5, DESPESAS!$J:$J, "<>Cancelada") | L38: =SUMIFS(DESPESAS!$H:$H, DESPESAS!$E:$E, "11.1 Serviços de contabilidade", DESPESAS!$L:$L, 9, DESPESAS!$M:$M, $E$5, DESPESAS!$J:$J, "<>Cancelada") | M38: =SUMIFS(DESPESAS!$H:$H, DESPESAS!$E:$E, "11.1 Serviços de contabilidade", DESPESAS!$L:$L, 10, DESPESAS!$M:$M, $E$5, DESPESAS!$J:$J, "<>Cancelada") | N38: =SUMIFS(DESPESAS!$H:$H, DESPESAS!$E:$E, "11.1 Serviços de contabilidade", DESPESAS!$L:$L, 11, DESPESAS!$M:$M, $E$5, DESPESAS!$J:$J, "<>Cancelada") | O38: =SUMIFS(DESPESAS!$H:$H, DESPESAS!$E:$E, "11.1 Serviços de contabilidade", DESPESAS!$L:$L, 12, DESPESAS!$M:$M, $E$5, DESPESAS!$J:$J, "<>Cancelada") | P38: =SUM(D38:O38) | Q38: =IFERROR(P38/$P$19, 0)
B39: 11.2 | C39: Manutenção de veículos | D39: =SUMIFS(DESPESAS!$H:$H, DESPESAS!$E:$E, "11.2 Manutenção de veículos", DESPESAS!$L:$L, 1, DESPESAS!$M:$M, $E$5, DESPESAS!$J:$J, "<>Cancelada") | E39: =SUMIFS(DESPESAS!$H:$H, DESPESAS!$E:$E, "11.2 Manutenção de veículos", DESPESAS!$L:$L, 2, DESPESAS!$M:$M, $E$5, DESPESAS!$J:$J, "<>Cancelada") | F39: =SUMIFS(DESPESAS!$H:$H, DESPESAS!$E:$E, "11.2 Manutenção de veículos", DESPESAS!$L:$L, 3, DESPESAS!$M:$M, $E$5, DESPESAS!$J:$J, "<>Cancelada") | G39: =SUMIFS(DESPESAS!$H:$H, DESPESAS!$E:$E, "11.2 Manutenção de veículos", DESPESAS!$L:$L, 4, DESPESAS!$M:$M, $E$5, DESPESAS!$J:$J, "<>Cancelada") | H39: =SUMIFS(DESPESAS!$H:$H, DESPESAS!$E:$E, "11.2 Manutenção de veículos", DESPESAS!$L:$L, 5, DESPESAS!$M:$M, $E$5, DESPESAS!$J:$J, "<>Cancelada") | I39: =SUMIFS(DESPESAS!$H:$H, DESPESAS!$E:$E, "11.2 Manutenção de veículos", DESPESAS!$L:$L, 6, DESPESAS!$M:$M, $E$5, DESPESAS!$J:$J, "<>Cancelada") | J39: =SUMIFS(DESPESAS!$H:$H, DESPESAS!$E:$E, "11.2 Manutenção de veículos", DESPESAS!$L:$L, 7, DESPESAS!$M:$M, $E$5, DESPESAS!$J:$J, "<>Cancelada") | K39: =SUMIFS(DESPESAS!$H:$H, DESPESAS!$E:$E, "11.2 Manutenção de veículos", DESPESAS!$L:$L, 8, DESPESAS!$M:$M, $E$5, DESPESAS!$J:$J, "<>Cancelada") | L39: =SUMIFS(DESPESAS!$H:$H, DESPESAS!$E:$E, "11.2 Manutenção de veículos", DESPESAS!$L:$L, 9, DESPESAS!$M:$M, $E$5, DESPESAS!$J:$J, "<>Cancelada") | M39: =SUMIFS(DESPESAS!$H:$H, DESPESAS!$E:$E, "11.2 Manutenção de veículos", DESPESAS!$L:$L, 10, DESPESAS!$M:$M, $E$5, DESPESAS!$J:$J, "<>Cancelada") | N39: =SUMIFS(DESPESAS!$H:$H, DESPESAS!$E:$E, "11.2 Manutenção de veículos", DESPESAS!$L:$L, 11, DESPESAS!$M:$M, $E$5, DESPESAS!$J:$J, "<>Cancelada") | O39: =SUMIFS(DESPESAS!$H:$H, DESPESAS!$E:$E, "11.2 Manutenção de veículos", DESPESAS!$L:$L, 12, DESPESAS!$M:$M, $E$5, DESPESAS!$J:$J, "<>Cancelada") | P39: =SUM(D39:O39) | Q39: =IFERROR(P39/$P$19, 0)
B40: 11.3 | C40: Manutenção da empresa | D40: =SUMIFS(DESPESAS!$H:$H, DESPESAS!$E:$E, "11.3 Manutenção da empresa", DESPESAS!$L:$L, 1, DESPESAS!$M:$M, $E$5, DESPESAS!$J:$J, "<>Cancelada") | E40: =SUMIFS(DESPESAS!$H:$H, DESPESAS!$E:$E, "11.3 Manutenção da empresa", DESPESAS!$L:$L, 2, DESPESAS!$M:$M, $E$5, DESPESAS!$J:$J, "<>Cancelada") | F40: =SUMIFS(DESPESAS!$H:$H, DESPESAS!$E:$E, "11.3 Manutenção da empresa", DESPESAS!$L:$L, 3, DESPESAS!$M:$M, $E$5, DESPESAS!$J:$J, "<>Cancelada") | G40: =SUMIFS(DESPESAS!$H:$H, DESPESAS!$E:$E, "11.3 Manutenção da empresa", DESPESAS!$L:$L, 4, DESPESAS!$M:$M, $E$5, DESPESAS!$J:$J, "<>Cancelada") | H40: =SUMIFS(DESPESAS!$H:$H, DESPESAS!$E:$E, "11.3 Manutenção da empresa", DESPESAS!$L:$L, 5, DESPESAS!$M:$M, $E$5, DESPESAS!$J:$J, "<>Cancelada") | I40: =SUMIFS(DESPESAS!$H:$H, DESPESAS!$E:$E, "11.3 Manutenção da empresa", DESPESAS!$L:$L, 6, DESPESAS!$M:$M, $E$5, DESPESAS!$J:$J, "<>Cancelada") | J40: =SUMIFS(DESPESAS!$H:$H, DESPESAS!$E:$E, "11.3 Manutenção da empresa", DESPESAS!$L:$L, 7, DESPESAS!$M:$M, $E$5, DESPESAS!$J:$J, "<>Cancelada") | K40: =SUMIFS(DESPESAS!$H:$H, DESPESAS!$E:$E, "11.3 Manutenção da empresa", DESPESAS!$L:$L, 8, DESPESAS!$M:$M, $E$5, DESPESAS!$J:$J, "<>Cancelada") | L40: =SUMIFS(DESPESAS!$H:$H, DESPESAS!$E:$E, "11.3 Manutenção da empresa", DESPESAS!$L:$L, 9, DESPESAS!$M:$M, $E$5, DESPESAS!$J:$J, "<>Cancelada") | M40: =SUMIFS(DESPESAS!$H:$H, DESPESAS!$E:$E, "11.3 Manutenção da empresa", DESPESAS!$L:$L, 10, DESPESAS!$M:$M, $E$5, DESPESAS!$J:$J, "<>Cancelada") | N40: =SUMIFS(DESPESAS!$H:$H, DESPESAS!$E:$E, "11.3 Manutenção da empresa", DESPESAS!$L:$L, 11, DESPESAS!$M:$M, $E$5, DESPESAS!$J:$J, "<>Cancelada") | O40: =SUMIFS(DESPESAS!$H:$H, DESPESAS!$E:$E, "11.3 Manutenção da empresa", DESPESAS!$L:$L, 12, DESPESAS!$M:$M, $E$5, DESPESAS!$J:$J, "<>Cancelada") | P40: =SUM(D40:O40) | Q40: =IFERROR(P40/$P$19, 0)
B41: 11.4 | C41: Seguro predial e instalação | D41: =SUMIFS(DESPESAS!$H:$H, DESPESAS!$E:$E, "11.4 Seguro predial e instalação", DESPESAS!$L:$L, 1, DESPESAS!$M:$M, $E$5, DESPESAS!$J:$J, "<>Cancelada") | E41: =SUMIFS(DESPESAS!$H:$H, DESPESAS!$E:$E, "11.4 Seguro predial e instalação", DESPESAS!$L:$L, 2, DESPESAS!$M:$M, $E$5, DESPESAS!$J:$J, "<>Cancelada") | F41: =SUMIFS(DESPESAS!$H:$H, DESPESAS!$E:$E, "11.4 Seguro predial e instalação", DESPESAS!$L:$L, 3, DESPESAS!$M:$M, $E$5, DESPESAS!$J:$J, "<>Cancelada") | G41: =SUMIFS(DESPESAS!$H:$H, DESPESAS!$E:$E, "11.4 Seguro predial e instalação", DESPESAS!$L:$L, 4, DESPESAS!$M:$M, $E$5, DESPESAS!$J:$J, "<>Cancelada") | H41: =SUMIFS(DESPESAS!$H:$H, DESPESAS!$E:$E, "11.4 Seguro predial e instalação", DESPESAS!$L:$L, 5, DESPESAS!$M:$M, $E$5, DESPESAS!$J:$J, "<>Cancelada") | I41: =SUMIFS(DESPESAS!$H:$H, DESPESAS!$E:$E, "11.4 Seguro predial e instalação", DESPESAS!$L:$L, 6, DESPESAS!$M:$M, $E$5, DESPESAS!$J:$J, "<>Cancelada") | J41: =SUMIFS(DESPESAS!$H:$H, DESPESAS!$E:$E, "11.4 Seguro predial e instalação", DESPESAS!$L:$L, 7, DESPESAS!$M:$M, $E$5, DESPESAS!$J:$J, "<>Cancelada") | K41: =SUMIFS(DESPESAS!$H:$H, DESPESAS!$E:$E, "11.4 Seguro predial e instalação", DESPESAS!$L:$L, 8, DESPESAS!$M:$M, $E$5, DESPESAS!$J:$J, "<>Cancelada") | L41: =SUMIFS(DESPESAS!$H:$H, DESPESAS!$E:$E, "11.4 Seguro predial e instalação", DESPESAS!$L:$L, 9, DESPESAS!$M:$M, $E$5, DESPESAS!$J:$J, "<>Cancelada") | M41: =SUMIFS(DESPESAS!$H:$H, DESPESAS!$E:$E, "11.4 Seguro predial e instalação", DESPESAS!$L:$L, 10, DESPESAS!$M:$M, $E$5, DESPESAS!$J:$J, "<>Cancelada") | N41: =SUMIFS(DESPESAS!$H:$H, DESPESAS!$E:$E, "11.4 Seguro predial e instalação", DESPESAS!$L:$L, 11, DESPESAS!$M:$M, $E$5, DESPESAS!$J:$J, "<>Cancelada") | O41: =SUMIFS(DESPESAS!$H:$H, DESPESAS!$E:$E, "11.4 Seguro predial e instalação", DESPESAS!$L:$L, 12, DESPESAS!$M:$M, $E$5, DESPESAS!$J:$J, "<>Cancelada") | P41: =SUM(D41:O41) | Q41: =IFERROR(P41/$P$19, 0)
B42: 11.5 | C42: Seguro produtos | D42: =SUMIFS(DESPESAS!$H:$H, DESPESAS!$E:$E, "11.5 Seguro produtos", DESPESAS!$L:$L, 1, DESPESAS!$M:$M, $E$5, DESPESAS!$J:$J, "<>Cancelada") | E42: =SUMIFS(DESPESAS!$H:$H, DESPESAS!$E:$E, "11.5 Seguro produtos", DESPESAS!$L:$L, 2, DESPESAS!$M:$M, $E$5, DESPESAS!$J:$J, "<>Cancelada") | F42: =SUMIFS(DESPESAS!$H:$H, DESPESAS!$E:$E, "11.5 Seguro produtos", DESPESAS!$L:$L, 3, DESPESAS!$M:$M, $E$5, DESPESAS!$J:$J, "<>Cancelada") | G42: =SUMIFS(DESPESAS!$H:$H, DESPESAS!$E:$E, "11.5 Seguro produtos", DESPESAS!$L:$L, 4, DESPESAS!$M:$M, $E$5, DESPESAS!$J:$J, "<>Cancelada") | H42: =SUMIFS(DESPESAS!$H:$H, DESPESAS!$E:$E, "11.5 Seguro produtos", DESPESAS!$L:$L, 5, DESPESAS!$M:$M, $E$5, DESPESAS!$J:$J, "<>Cancelada") | I42: =SUMIFS(DESPESAS!$H:$H, DESPESAS!$E:$E, "11.5 Seguro produtos", DESPESAS!$L:$L, 6, DESPESAS!$M:$M, $E$5, DESPESAS!$J:$J, "<>Cancelada") | J42: =SUMIFS(DESPESAS!$H:$H, DESPESAS!$E:$E, "11.5 Seguro produtos", DESPESAS!$L:$L, 7, DESPESAS!$M:$M, $E$5, DESPESAS!$J:$J, "<>Cancelada") | K42: =SUMIFS(DESPESAS!$H:$H, DESPESAS!$E:$E, "11.5 Seguro produtos", DESPESAS!$L:$L, 8, DESPESAS!$M:$M, $E$5, DESPESAS!$J:$J, "<>Cancelada") | L42: =SUMIFS(DESPESAS!$H:$H, DESPESAS!$E:$E, "11.5 Seguro produtos", DESPESAS!$L:$L, 9, DESPESAS!$M:$M, $E$5, DESPESAS!$J:$J, "<>Cancelada") | M42: =SUMIFS(DESPESAS!$H:$H, DESPESAS!$E:$E, "11.5 Seguro produtos", DESPESAS!$L:$L, 10, DESPESAS!$M:$M, $E$5, DESPESAS!$J:$J, "<>Cancelada") | N42: =SUMIFS(DESPESAS!$H:$H, DESPESAS!$E:$E, "11.5 Seguro produtos", DESPESAS!$L:$L, 11, DESPESAS!$M:$M, $E$5, DESPESAS!$J:$J, "<>Cancelada") | O42: =SUMIFS(DESPESAS!$H:$H, DESPESAS!$E:$E, "11.5 Seguro produtos", DESPESAS!$L:$L, 12, DESPESAS!$M:$M, $E$5, DESPESAS!$J:$J, "<>Cancelada") | P42: =SUM(D42:O42) | Q42: =IFERROR(P42/$P$19, 0)
B43: 11.6 | C43: Depreciação | D43: =SUMIFS(DESPESAS!$H:$H, DESPESAS!$E:$E, "11.6 Depreciação", DESPESAS!$L:$L, 1, DESPESAS!$M:$M, $E$5, DESPESAS!$J:$J, "<>Cancelada") | E43: =SUMIFS(DESPESAS!$H:$H, DESPESAS!$E:$E, "11.6 Depreciação", DESPESAS!$L:$L, 2, DESPESAS!$M:$M, $E$5, DESPESAS!$J:$J, "<>Cancelada") | F43: =SUMIFS(DESPESAS!$H:$H, DESPESAS!$E:$E, "11.6 Depreciação", DESPESAS!$L:$L, 3, DESPESAS!$M:$M, $E$5, DESPESAS!$J:$J, "<>Cancelada") | G43: =SUMIFS(DESPESAS!$H:$H, DESPESAS!$E:$E, "11.6 Depreciação", DESPESAS!$L:$L, 4, DESPESAS!$M:$M, $E$5, DESPESAS!$J:$J, "<>Cancelada") | H43: =SUMIFS(DESPESAS!$H:$H, DESPESAS!$E:$E, "11.6 Depreciação", DESPESAS!$L:$L, 5, DESPESAS!$M:$M, $E$5, DESPESAS!$J:$J, "<>Cancelada") | I43: =SUMIFS(DESPESAS!$H:$H, DESPESAS!$E:$E, "11.6 Depreciação", DESPESAS!$L:$L, 6, DESPESAS!$M:$M, $E$5, DESPESAS!$J:$J, "<>Cancelada") | J43: =SUMIFS(DESPESAS!$H:$H, DESPESAS!$E:$E, "11.6 Depreciação", DESPESAS!$L:$L, 7, DESPESAS!$M:$M, $E$5, DESPESAS!$J:$J, "<>Cancelada") | K43: =SUMIFS(DESPESAS!$H:$H, DESPESAS!$E:$E, "11.6 Depreciação", DESPESAS!$L:$L, 8, DESPESAS!$M:$M, $E$5, DESPESAS!$J:$J, "<>Cancelada") | L43: =SUMIFS(DESPESAS!$H:$H, DESPESAS!$E:$E, "11.6 Depreciação", DESPESAS!$L:$L, 9, DESPESAS!$M:$M, $E$5, DESPESAS!$J:$J, "<>Cancelada") | M43: =SUMIFS(DESPESAS!$H:$H, DESPESAS!$E:$E, "11.6 Depreciação", DESPESAS!$L:$L, 10, DESPESAS!$M:$M, $E$5, DESPESAS!$J:$J, "<>Cancelada") | N43: =SUMIFS(DESPESAS!$H:$H, DESPESAS!$E:$E, "11.6 Depreciação", DESPESAS!$L:$L, 11, DESPESAS!$M:$M, $E$5, DESPESAS!$J:$J, "<>Cancelada") | O43: =SUMIFS(DESPESAS!$H:$H, DESPESAS!$E:$E, "11.6 Depreciação", DESPESAS!$L:$L, 12, DESPESAS!$M:$M, $E$5, DESPESAS!$J:$J, "<>Cancelada") | P43: =SUM(D43:O43) | Q43: =IFERROR(P43/$P$19, 0)
B44: 11.7 | C44: Custo da Venda de Bens e Direitos do Ativo Não Circulante | D44: =SUMIFS(DESPESAS!$H:$H, DESPESAS!$E:$E, "11.7 Custo da Venda de Bens e Direitos do Ativo Não Circulante", DESPESAS!$L:$L, 1, DESPESAS!$M:$M, $E$5, DESPESAS!$J:$J, "<>Cancelada") | E44: =SUMIFS(DESPESAS!$H:$H, DESPESAS!$E:$E, "11.7 Custo da Venda de Bens e Direitos do Ativo Não Circulante", DESPESAS!$L:$L, 2, DESPESAS!$M:$M, $E$5, DESPESAS!$J:$J, "<>Cancelada") | F44: =SUMIFS(DESPESAS!$H:$H, DESPESAS!$E:$E, "11.7 Custo da Venda de Bens e Direitos do Ativo Não Circulante", DESPESAS!$L:$L, 3, DESPESAS!$M:$M, $E$5, DESPESAS!$J:$J, "<>Cancelada") | G44: =SUMIFS(DESPESAS!$H:$H, DESPESAS!$E:$E, "11.7 Custo da Venda de Bens e Direitos do Ativo Não Circulante", DESPESAS!$L:$L, 4, DESPESAS!$M:$M, $E$5, DESPESAS!$J:$J, "<>Cancelada") | H44: =SUMIFS(DESPESAS!$H:$H, DESPESAS!$E:$E, "11.7 Custo da Venda de Bens e Direitos do Ativo Não Circulante", DESPESAS!$L:$L, 5, DESPESAS!$M:$M, $E$5, DESPESAS!$J:$J, "<>Cancelada") | I44: =SUMIFS(DESPESAS!$H:$H, DESPESAS!$E:$E, "11.7 Custo da Venda de Bens e Direitos do Ativo Não Circulante", DESPESAS!$L:$L, 6, DESPESAS!$M:$M, $E$5, DESPESAS!$J:$J, "<>Cancelada") | J44: =SUMIFS(DESPESAS!$H:$H, DESPESAS!$E:$E, "11.7 Custo da Venda de Bens e Direitos do Ativo Não Circulante", DESPESAS!$L:$L, 7, DESPESAS!$M:$M, $E$5, DESPESAS!$J:$J, "<>Cancelada") | K44: =SUMIFS(DESPESAS!$H:$H, DESPESAS!$E:$E, "11.7 Custo da Venda de Bens e Direitos do Ativo Não Circulante", DESPESAS!$L:$L, 8, DESPESAS!$M:$M, $E$5, DESPESAS!$J:$J, "<>Cancelada") | L44: =SUMIFS(DESPESAS!$H:$H, DESPESAS!$E:$E, "11.7 Custo da Venda de Bens e Direitos do Ativo Não Circulante", DESPESAS!$L:$L, 9, DESPESAS!$M:$M, $E$5, DESPESAS!$J:$J, "<>Cancelada") | M44: =SUMIFS(DESPESAS!$H:$H, DESPESAS!$E:$E, "11.7 Custo da Venda de Bens e Direitos do Ativo Não Circulante", DESPESAS!$L:$L, 10, DESPESAS!$M:$M, $E$5, DESPESAS!$J:$J, "<>Cancelada") | N44: =SUMIFS(DESPESAS!$H:$H, DESPESAS!$E:$E, "11.7 Custo da Venda de Bens e Direitos do Ativo Não Circulante", DESPESAS!$L:$L, 11, DESPESAS!$M:$M, $E$5, DESPESAS!$J:$J, "<>Cancelada") | O44: =SUMIFS(DESPESAS!$H:$H, DESPESAS!$E:$E, "11.7 Custo da Venda de Bens e Direitos do Ativo Não Circulante", DESPESAS!$L:$L, 12, DESPESAS!$M:$M, $E$5, DESPESAS!$J:$J, "<>Cancelada") | P44: =SUM(D44:O44) | Q44: =IFERROR(P44/$P$19, 0)
B45: 12 | C45: RESULTADO OPERACIONAL ANTES DO IR/CSLL (5-6+9+10-11) | D45: =D23-D24+D33+D34-D37 | E45: =E23-E24+E33+E34-E37 | F45: =F23-F24+F33+F34-F37 | G45: =G23-G24+G33+G34-G37 | H45: =H23-H24+H33+H34-H37 | I45: =I23-I24+I33+I34-I37 | J45: =J23-J24+J33+J34-J37 | K45: =K23-K24+K33+K34-K37 | ... O45: =O23-O24+O33+O34-O37 | P45: =SUM(D45:O45) | Q45: =IFERROR(P45/$P$19, 0)
B46: 13 | C46: Provisão para IR e CSLL | D46: =SUM(D47:D48) | E46: =SUM(E47:E48) | F46: =SUM(F47:F48) | G46: =SUM(G47:G48) | H46: =SUM(H47:H48) | I46: =SUM(I47:I48) | J46: =SUM(J47:J48) | K46: =SUM(K47:K48) | ... O46: =SUM(O47:O48) | P46: =SUM(D46:O46) | Q46: =IFERROR(P46/$P$19, 0)
B47: 13.1 | C47: Imposto de Renda | D47: =SUMIFS(DESPESAS!$H:$H, DESPESAS!$E:$E, "13.1 Imposto de Renda", DESPESAS!$L:$L, 1, DESPESAS!$M:$M, $E$5, DESPESAS!$J:$J, "<>Cancelada") | E47: =SUMIFS(DESPESAS!$H:$H, DESPESAS!$E:$E, "13.1 Imposto de Renda", DESPESAS!$L:$L, 2, DESPESAS!$M:$M, $E$5, DESPESAS!$J:$J, "<>Cancelada") | F47: =SUMIFS(DESPESAS!$H:$H, DESPESAS!$E:$E, "13.1 Imposto de Renda", DESPESAS!$L:$L, 3, DESPESAS!$M:$M, $E$5, DESPESAS!$J:$J, "<>Cancelada") | G47: =SUMIFS(DESPESAS!$H:$H, DESPESAS!$E:$E, "13.1 Imposto de Renda", DESPESAS!$L:$L, 4, DESPESAS!$M:$M, $E$5, DESPESAS!$J:$J, "<>Cancelada") | H47: =SUMIFS(DESPESAS!$H:$H, DESPESAS!$E:$E, "13.1 Imposto de Renda", DESPESAS!$L:$L, 5, DESPESAS!$M:$M, $E$5, DESPESAS!$J:$J, "<>Cancelada") | I47: =SUMIFS(DESPESAS!$H:$H, DESPESAS!$E:$E, "13.1 Imposto de Renda", DESPESAS!$L:$L, 6, DESPESAS!$M:$M, $E$5, DESPESAS!$J:$J, "<>Cancelada") | J47: =SUMIFS(DESPESAS!$H:$H, DESPESAS!$E:$E, "13.1 Imposto de Renda", DESPESAS!$L:$L, 7, DESPESAS!$M:$M, $E$5, DESPESAS!$J:$J, "<>Cancelada") | K47: =SUMIFS(DESPESAS!$H:$H, DESPESAS!$E:$E, "13.1 Imposto de Renda", DESPESAS!$L:$L, 8, DESPESAS!$M:$M, $E$5, DESPESAS!$J:$J, "<>Cancelada") | L47: =SUMIFS(DESPESAS!$H:$H, DESPESAS!$E:$E, "13.1 Imposto de Renda", DESPESAS!$L:$L, 9, DESPESAS!$M:$M, $E$5, DESPESAS!$J:$J, "<>Cancelada") | M47: =SUMIFS(DESPESAS!$H:$H, DESPESAS!$E:$E, "13.1 Imposto de Renda", DESPESAS!$L:$L, 10, DESPESAS!$M:$M, $E$5, DESPESAS!$J:$J, "<>Cancelada") | N47: =SUMIFS(DESPESAS!$H:$H, DESPESAS!$E:$E, "13.1 Imposto de Renda", DESPESAS!$L:$L, 11, DESPESAS!$M:$M, $E$5, DESPESAS!$J:$J, "<>Cancelada") | O47: =SUMIFS(DESPESAS!$H:$H, DESPESAS!$E:$E, "13.1 Imposto de Renda", DESPESAS!$L:$L, 12, DESPESAS!$M:$M, $E$5, DESPESAS!$J:$J, "<>Cancelada") | P47: =SUM(D47:O47) | Q47: =IFERROR(P47/$P$19, 0)
B48: 13.2 | C48: Contribuição Social sobre o Lucro Líquido | D48: =SUMIFS(DESPESAS!$H:$H, DESPESAS!$E:$E, "13.2 Contribuição Social sobre o Lucro Líquido", DESPESAS!$L:$L, 1, DESPESAS!$M:$M, $E$5, DESPESAS!$J:$J, "<>Cancelada") | E48: =SUMIFS(DESPESAS!$H:$H, DESPESAS!$E:$E, "13.2 Contribuição Social sobre o Lucro Líquido", DESPESAS!$L:$L, 2, DESPESAS!$M:$M, $E$5, DESPESAS!$J:$J, "<>Cancelada") | F48: =SUMIFS(DESPESAS!$H:$H, DESPESAS!$E:$E, "13.2 Contribuição Social sobre o Lucro Líquido", DESPESAS!$L:$L, 3, DESPESAS!$M:$M, $E$5, DESPESAS!$J:$J, "<>Cancelada") | G48: =SUMIFS(DESPESAS!$H:$H, DESPESAS!$E:$E, "13.2 Contribuição Social sobre o Lucro Líquido", DESPESAS!$L:$L, 4, DESPESAS!$M:$M, $E$5, DESPESAS!$J:$J, "<>Cancelada") | H48: =SUMIFS(DESPESAS!$H:$H, DESPESAS!$E:$E, "13.2 Contribuição Social sobre o Lucro Líquido", DESPESAS!$L:$L, 5, DESPESAS!$M:$M, $E$5, DESPESAS!$J:$J, "<>Cancelada") | I48: =SUMIFS(DESPESAS!$H:$H, DESPESAS!$E:$E, "13.2 Contribuição Social sobre o Lucro Líquido", DESPESAS!$L:$L, 6, DESPESAS!$M:$M, $E$5, DESPESAS!$J:$J, "<>Cancelada") | J48: =SUMIFS(DESPESAS!$H:$H, DESPESAS!$E:$E, "13.2 Contribuição Social sobre o Lucro Líquido", DESPESAS!$L:$L, 7, DESPESAS!$M:$M, $E$5, DESPESAS!$J:$J, "<>Cancelada") | K48: =SUMIFS(DESPESAS!$H:$H, DESPESAS!$E:$E, "13.2 Contribuição Social sobre o Lucro Líquido", DESPESAS!$L:$L, 8, DESPESAS!$M:$M, $E$5, DESPESAS!$J:$J, "<>Cancelada") | L48: =SUMIFS(DESPESAS!$H:$H, DESPESAS!$E:$E, "13.2 Contribuição Social sobre o Lucro Líquido", DESPESAS!$L:$L, 9, DESPESAS!$M:$M, $E$5, DESPESAS!$J:$J, "<>Cancelada") | M48: =SUMIFS(DESPESAS!$H:$H, DESPESAS!$E:$E, "13.2 Contribuição Social sobre o Lucro Líquido", DESPESAS!$L:$L, 10, DESPESAS!$M:$M, $E$5, DESPESAS!$J:$J, "<>Cancelada") | N48: =SUMIFS(DESPESAS!$H:$H, DESPESAS!$E:$E, "13.2 Contribuição Social sobre o Lucro Líquido", DESPESAS!$L:$L, 11, DESPESAS!$M:$M, $E$5, DESPESAS!$J:$J, "<>Cancelada") | O48: =SUMIFS(DESPESAS!$H:$H, DESPESAS!$E:$E, "13.2 Contribuição Social sobre o Lucro Líquido", DESPESAS!$L:$L, 12, DESPESAS!$M:$M, $E$5, DESPESAS!$J:$J, "<>Cancelada") | P48: =SUM(D48:O48) | Q48: =IFERROR(P48/$P$19, 0)
B49: 14 | C49: RESULTADO OPERACIONAL LÍQUIDO (12 - 13) | D49: =D45-D46 | E49: =E45-E46 | F49: =F45-F46 | G49: =G45-G46 | H49: =H45-H46 | I49: =I45-I46 | J49: =J45-J46 | K49: =K45-K46 | ... O49: =O45-O46 | P49: =SUM(D49:O49) | Q49: =IFERROR(P49/$P$19, 0)
B51: 📈 INDICADORES DE RESULTADOS E RENTABILIDADE MENSAL (%)
B52: IND.1 | C52: Margem Bruta (Resultado Bruto / Vendas Líquidas) | D52: =IFERROR(D23/D$19, 0) | E52: =IFERROR(E23/E$19, 0) | F52: =IFERROR(F23/F$19, 0) | G52: =IFERROR(G23/G$19, 0) | H52: =IFERROR(H23/H$19, 0) | I52: =IFERROR(I23/I$19, 0) | J52: =IFERROR(J23/J$19, 0) | K52: =IFERROR(K23/K$19, 0) | ... P52: =IFERROR(P23/P$19, 0) | Q52: =P52
B53: IND.2 | C53: Margem Operacional (Resultado Operacional / Vendas Líquidas) | D53: =IFERROR(D45/D$19, 0) | E53: =IFERROR(E45/E$19, 0) | F53: =IFERROR(F45/F$19, 0) | G53: =IFERROR(G45/G$19, 0) | H53: =IFERROR(H45/H$19, 0) | I53: =IFERROR(I45/I$19, 0) | J53: =IFERROR(J45/J$19, 0) | K53: =IFERROR(K45/K$19, 0) | ... P53: =IFERROR(P45/P$19, 0) | Q53: =P53
B54: IND.3 | C54: Lucratividade Líquida (Resultado Líquido / Vendas Líquidas) | D54: =IFERROR(D49/D$19, 0) | E54: =IFERROR(E49/E$19, 0) | F54: =IFERROR(F49/F$19, 0) | G54: =IFERROR(G49/G$19, 0) | H54: =IFERROR(H49/H$19, 0) | I54: =IFERROR(I49/I$19, 0) | J54: =IFERROR(J49/J$19, 0) | K54: =IFERROR(K49/K$19, 0) | ... P54: =IFERROR(P49/P$19, 0) | Q54: =P54

Sheet FLUXO_CAIXA
B2: 💰 DEMONSTRATIVO DE FLUXO DE CAIXA E RESULTADOS (ENTRADAS VS SAÍDAS)
B5: EMPRESA: | C5: =CONFIG!B2 | D5: ANO: | E5: 2026
B7: 🟢 TOTAL ENTRADAS (ANO) | D7: 🔴 TOTAL SAÍDAS PAGAS | G7: 💰 RESULTADO CAIXA (ANO) | J7: ⏳ DESPESAS PENDENTES (A PAGAR) | N7: 📊 COMPROMETIMENTO CAIXA (%)
B8: =P17 | D8: =P39 | G8: =P41 | J8: =SUMIFS(DESPESAS!H:H, DESPESAS!J:J, "Pendente", DESPESAS!M:M, E5) | N8: =IFERROR(P39/P17,0)
B11: ITEM | C11: ENTRADAS (RECEITAS) | D11: JAN | E11: FEV | F11: MAR | G11: ABR | H11: MAI | I11: JUN | J11: JUL | K11: AGO | L11: SET | M11: OUT | N11: NOV | O11: DEZ | P11: TOTAL ANUAL
B12: 1.1 | C12: Vendas de produtos (com nota fiscal / PDV) | D12: =MAX(0, APURACAO_RESULTADOS!D13 - APURACAO_RESULTADOS!D18) | E12: =MAX(0, APURACAO_RESULTADOS!E13 - APURACAO_RESULTADOS!E18) | F12: =MAX(0, APURACAO_RESULTADOS!F13 - APURACAO_RESULTADOS!F18) | G12: =MAX(0, APURACAO_RESULTADOS!G13 - APURACAO_RESULTADOS!G18) | H12: =MAX(0, APURACAO_RESULTADOS!H13 - APURACAO_RESULTADOS!H18) | I12: =MAX(0, APURACAO_RESULTADOS!I13 - APURACAO_RESULTADOS!I18) | J12: =MAX(0, APURACAO_RESULTADOS!J13 - APURACAO_RESULTADOS!J18) | K12: =MAX(0, APURACAO_RESULTADOS!K13 - APURACAO_RESULTADOS!K18) | ... O12: =MAX(0, APURACAO_RESULTADOS!O13 - APURACAO_RESULTADOS!O18) | P12: =SUM(D12:O12)
B13: 1.2 | C13: Vendas de produtos (sem nota fiscal)* | D13: 0 | E13: 0 | F13: 0 | G13: 0 | H13: 0 | I13: 0 | J13: 0 | K13: 0 | L13: 0 | M13: 0 | N13: 0 | O13: 0 | P13: =SUM(D13:O13)
B14: 1.3 | C14: Prestação de serviços (com nota fiscal / PDV) | D14: =APURACAO_RESULTADOS!D14 | E14: =APURACAO_RESULTADOS!E14 | F14: =APURACAO_RESULTADOS!F14 | G14: =APURACAO_RESULTADOS!G14 | H14: =APURACAO_RESULTADOS!H14 | I14: =APURACAO_RESULTADOS!I14 | J14: =APURACAO_RESULTADOS!J14 | K14: =APURACAO_RESULTADOS!K14 | ... O14: =APURACAO_RESULTADOS!O14 | P14: =SUM(D14:O14)
B15: 1.4 | C15: Prestação de serviços (sem nota fiscal)* | D15: 0 | E15: 0 | F15: 0 | G15: 0 | H15: 0 | I15: 0 | J15: 0 | K15: 0 | L15: 0 | M15: 0 | N15: 0 | O15: 0 | P15: =SUM(D15:O15)
B16: 1.5 | C16: Outras receitas (aplicações no banco, etc.) | D16: =APURACAO_RESULTADOS!D27 + APURACAO_RESULTADOS!D34 | E16: =APURACAO_RESULTADOS!E27 + APURACAO_RESULTADOS!E34 | F16: =APURACAO_RESULTADOS!F27 + APURACAO_RESULTADOS!F34 | G16: =APURACAO_RESULTADOS!G27 + APURACAO_RESULTADOS!G34 | H16: =APURACAO_RESULTADOS!H27 + APURACAO_RESULTADOS!H34 | I16: =APURACAO_RESULTADOS!I27 + APURACAO_RESULTADOS!I34 | J16: =APURACAO_RESULTADOS!J27 + APURACAO_RESULTADOS!J34 | K16: =APURACAO_RESULTADOS!K27 + APURACAO_RESULTADOS!K34 | ... O16: =APURACAO_RESULTADOS!O27 + APURACAO_RESULTADOS!O34 | P16: =SUM(D16:O16)
B17: 1 | C17: TOTAL DE ENTRADAS | D17: =SUM(D12:D16) | E17: =SUM(E12:E16) | F17: =SUM(F12:F16) | G17: =SUM(G12:G16) | H17: =SUM(H12:H16) | I17: =SUM(I12:I16) | J17: =SUM(J12:J16) | K17: =SUM(K12:K16) | ... P17: =SUM(P12:P16)
B19: ITEM | C19: SAÍDAS (GASTOS) | D19: JAN | E19: FEV | F19: MAR | G19: ABR | H19: MAI | I19: JUN | J19: JUL | K19: AGO | L19: SET | M19: OUT | N19: NOV | O19: DEZ | P19: TOTAL ANUAL
B20: 2.1 | C20: Retirada do(s) proprietário(s) ** | D20: =SUMIFS(DESPESAS!$H:$H, DESPESAS!$F:$F, "Retirada do(s) proprietário(s)", DESPESAS!$N:$N, 1, DESPESAS!$O:$O, $E$5, DESPESAS!$J:$J, "Paga") | E20: =SUMIFS(DESPESAS!$H:$H, DESPESAS!$F:$F, "Retirada do(s) proprietário(s)", DESPESAS!$N:$N, 2, DESPESAS!$O:$O, $E$5, DESPESAS!$J:$J, "Paga") | F20: =SUMIFS(DESPESAS!$H:$H, DESPESAS!$F:$F, "Retirada do(s) proprietário(s)", DESPESAS!$N:$N, 3, DESPESAS!$O:$O, $E$5, DESPESAS!$J:$J, "Paga") | G20: =SUMIFS(DESPESAS!$H:$H, DESPESAS!$F:$F, "Retirada do(s) proprietário(s)", DESPESAS!$N:$N, 4, DESPESAS!$O:$O, $E$5, DESPESAS!$J:$J, "Paga") | H20: =SUMIFS(DESPESAS!$H:$H, DESPESAS!$F:$F, "Retirada do(s) proprietário(s)", DESPESAS!$N:$N, 5, DESPESAS!$O:$O, $E$5, DESPESAS!$J:$J, "Paga") | I20: =SUMIFS(DESPESAS!$H:$H, DESPESAS!$F:$F, "Retirada do(s) proprietário(s)", DESPESAS!$N:$N, 6, DESPESAS!$O:$O, $E$5, DESPESAS!$J:$J, "Paga") | J20: =SUMIFS(DESPESAS!$H:$H, DESPESAS!$F:$F, "Retirada do(s) proprietário(s)", DESPESAS!$N:$N, 7, DESPESAS!$O:$O, $E$5, DESPESAS!$J:$J, "Paga") | K20: =SUMIFS(DESPESAS!$H:$H, DESPESAS!$F:$F, "Retirada do(s) proprietário(s)", DESPESAS!$N:$N, 8, DESPESAS!$O:$O, $E$5, DESPESAS!$J:$J, "Paga") | L20: =SUMIFS(DESPESAS!$H:$H, DESPESAS!$F:$F, "Retirada do(s) proprietário(s)", DESPESAS!$N:$N, 9, DESPESAS!$O:$O, $E$5, DESPESAS!$J:$J, "Paga") | M20: =SUMIFS(DESPESAS!$H:$H, DESPESAS!$F:$F, "Retirada do(s) proprietário(s)", DESPESAS!$N:$N, 10, DESPESAS!$O:$O, $E$5, DESPESAS!$J:$J, "Paga") | N20: =SUMIFS(DESPESAS!$H:$H, DESPESAS!$F:$F, "Retirada do(s) proprietário(s)", DESPESAS!$N:$N, 11, DESPESAS!$O:$O, $E$5, DESPESAS!$J:$J, "Paga") | O20: =SUMIFS(DESPESAS!$H:$H, DESPESAS!$F:$F, "Retirada do(s) proprietário(s)", DESPESAS!$N:$N, 12, DESPESAS!$O:$O, $E$5, DESPESAS!$J:$J, "Paga") | P20: =SUM(D20:O20)
B21: 2.2 | C21: Gastos com produtos para venda | D21: =SUMIFS(DESPESAS!$H:$H, DESPESAS!$F:$F, "Gastos com produtos para venda", DESPESAS!$N:$N, 1, DESPESAS!$O:$O, $E$5, DESPESAS!$J:$J, "Paga") | E21: =SUMIFS(DESPESAS!$H:$H, DESPESAS!$F:$F, "Gastos com produtos para venda", DESPESAS!$N:$N, 2, DESPESAS!$O:$O, $E$5, DESPESAS!$J:$J, "Paga") | F21: =SUMIFS(DESPESAS!$H:$H, DESPESAS!$F:$F, "Gastos com produtos para venda", DESPESAS!$N:$N, 3, DESPESAS!$O:$O, $E$5, DESPESAS!$J:$J, "Paga") | G21: =SUMIFS(DESPESAS!$H:$H, DESPESAS!$F:$F, "Gastos com produtos para venda", DESPESAS!$N:$N, 4, DESPESAS!$O:$O, $E$5, DESPESAS!$J:$J, "Paga") | H21: =SUMIFS(DESPESAS!$H:$H, DESPESAS!$F:$F, "Gastos com produtos para venda", DESPESAS!$N:$N, 5, DESPESAS!$O:$O, $E$5, DESPESAS!$J:$J, "Paga") | I21: =SUMIFS(DESPESAS!$H:$H, DESPESAS!$F:$F, "Gastos com produtos para venda", DESPESAS!$N:$N, 6, DESPESAS!$O:$O, $E$5, DESPESAS!$J:$J, "Paga") | J21: =SUMIFS(DESPESAS!$H:$H, DESPESAS!$F:$F, "Gastos com produtos para venda", DESPESAS!$N:$N, 7, DESPESAS!$O:$O, $E$5, DESPESAS!$J:$J, "Paga") | K21: =SUMIFS(DESPESAS!$H:$H, DESPESAS!$F:$F, "Gastos com produtos para venda", DESPESAS!$N:$N, 8, DESPESAS!$O:$O, $E$5, DESPESAS!$J:$J, "Paga") | L21: =SUMIFS(DESPESAS!$H:$H, DESPESAS!$F:$F, "Gastos com produtos para venda", DESPESAS!$N:$N, 9, DESPESAS!$O:$O, $E$5, DESPESAS!$J:$J, "Paga") | M21: =SUMIFS(DESPESAS!$H:$H, DESPESAS!$F:$F, "Gastos com produtos para venda", DESPESAS!$N:$N, 10, DESPESAS!$O:$O, $E$5, DESPESAS!$J:$J, "Paga") | N21: =SUMIFS(DESPESAS!$H:$H, DESPESAS!$F:$F, "Gastos com produtos para venda", DESPESAS!$N:$N, 11, DESPESAS!$O:$O, $E$5, DESPESAS!$J:$J, "Paga") | O21: =SUMIFS(DESPESAS!$H:$H, DESPESAS!$F:$F, "Gastos com produtos para venda", DESPESAS!$N:$N, 12, DESPESAS!$O:$O, $E$5, DESPESAS!$J:$J, "Paga") | P21: =SUM(D21:O21)
B22: 2.3 | C22: Gastos com serviços prestados *** | D22: =SUMIFS(DESPESAS!$H:$H, DESPESAS!$F:$F, "Gastos com serviços prestados", DESPESAS!$N:$N, 1, DESPESAS!$O:$O, $E$5, DESPESAS!$J:$J, "Paga") | E22: =SUMIFS(DESPESAS!$H:$H, DESPESAS!$F:$F, "Gastos com serviços prestados", DESPESAS!$N:$N, 2, DESPESAS!$O:$O, $E$5, DESPESAS!$J:$J, "Paga") | F22: =SUMIFS(DESPESAS!$H:$H, DESPESAS!$F:$F, "Gastos com serviços prestados", DESPESAS!$N:$N, 3, DESPESAS!$O:$O, $E$5, DESPESAS!$J:$J, "Paga") | G22: =SUMIFS(DESPESAS!$H:$H, DESPESAS!$F:$F, "Gastos com serviços prestados", DESPESAS!$N:$N, 4, DESPESAS!$O:$O, $E$5, DESPESAS!$J:$J, "Paga") | H22: =SUMIFS(DESPESAS!$H:$H, DESPESAS!$F:$F, "Gastos com serviços prestados", DESPESAS!$N:$N, 5, DESPESAS!$O:$O, $E$5, DESPESAS!$J:$J, "Paga") | I22: =SUMIFS(DESPESAS!$H:$H, DESPESAS!$F:$F, "Gastos com serviços prestados", DESPESAS!$N:$N, 6, DESPESAS!$O:$O, $E$5, DESPESAS!$J:$J, "Paga") | J22: =SUMIFS(DESPESAS!$H:$H, DESPESAS!$F:$F, "Gastos com serviços prestados", DESPESAS!$N:$N, 7, DESPESAS!$O:$O, $E$5, DESPESAS!$J:$J, "Paga") | K22: =SUMIFS(DESPESAS!$H:$H, DESPESAS!$F:$F, "Gastos com serviços prestados", DESPESAS!$N:$N, 8, DESPESAS!$O:$O, $E$5, DESPESAS!$J:$J, "Paga") | L22: =SUMIFS(DESPESAS!$H:$H, DESPESAS!$F:$F, "Gastos com serviços prestados", DESPESAS!$N:$N, 9, DESPESAS!$O:$O, $E$5, DESPESAS!$J:$J, "Paga") | M22: =SUMIFS(DESPESAS!$H:$H, DESPESAS!$F:$F, "Gastos com serviços prestados", DESPESAS!$N:$N, 10, DESPESAS!$O:$O, $E$5, DESPESAS!$J:$J, "Paga") | N22: =SUMIFS(DESPESAS!$H:$H, DESPESAS!$F:$F, "Gastos com serviços prestados", DESPESAS!$N:$N, 11, DESPESAS!$O:$O, $E$5, DESPESAS!$J:$J, "Paga") | O22: =SUMIFS(DESPESAS!$H:$H, DESPESAS!$F:$F, "Gastos com serviços prestados", DESPESAS!$N:$N, 12, DESPESAS!$O:$O, $E$5, DESPESAS!$J:$J, "Paga") | P22: =SUM(D22:O22)
B23: 2.4 | C23: Carnê de arrecadação - MEI | D23: =SUMIFS(DESPESAS!$H:$H, DESPESAS!$F:$F, "Carnê de arrecadação - MEI", DESPESAS!$N:$N, 1, DESPESAS!$O:$O, $E$5, DESPESAS!$J:$J, "Paga") | E23: =SUMIFS(DESPESAS!$H:$H, DESPESAS!$F:$F, "Carnê de arrecadação - MEI", DESPESAS!$N:$N, 2, DESPESAS!$O:$O, $E$5, DESPESAS!$J:$J, "Paga") | F23: =SUMIFS(DESPESAS!$H:$H, DESPESAS!$F:$F, "Carnê de arrecadação - MEI", DESPESAS!$N:$N, 3, DESPESAS!$O:$O, $E$5, DESPESAS!$J:$J, "Paga") | G23: =SUMIFS(DESPESAS!$H:$H, DESPESAS!$F:$F, "Carnê de arrecadação - MEI", DESPESAS!$N:$N, 4, DESPESAS!$O:$O, $E$5, DESPESAS!$J:$J, "Paga") | H23: =SUMIFS(DESPESAS!$H:$H, DESPESAS!$F:$F, "Carnê de arrecadação - MEI", DESPESAS!$N:$N, 5, DESPESAS!$O:$O, $E$5, DESPESAS!$J:$J, "Paga") | I23: =SUMIFS(DESPESAS!$H:$H, DESPESAS!$F:$F, "Carnê de arrecadação - MEI", DESPESAS!$N:$N, 6, DESPESAS!$O:$O, $E$5, DESPESAS!$J:$J, "Paga") | J23: =SUMIFS(DESPESAS!$H:$H, DESPESAS!$F:$F, "Carnê de arrecadação - MEI", DESPESAS!$N:$N, 7, DESPESAS!$O:$O, $E$5, DESPESAS!$J:$J, "Paga") | K23: =SUMIFS(DESPESAS!$H:$H, DESPESAS!$F:$F, "Carnê de arrecadação - MEI", DESPESAS!$N:$N, 8, DESPESAS!$O:$O, $E$5, DESPESAS!$J:$J, "Paga") | L23: =SUMIFS(DESPESAS!$H:$H, DESPESAS!$F:$F, "Carnê de arrecadação - MEI", DESPESAS!$N:$N, 9, DESPESAS!$O:$O, $E$5, DESPESAS!$J:$J, "Paga") | M23: =SUMIFS(DESPESAS!$H:$H, DESPESAS!$F:$F, "Carnê de arrecadação - MEI", DESPESAS!$N:$N, 10, DESPESAS!$O:$O, $E$5, DESPESAS!$J:$J, "Paga") | N23: =SUMIFS(DESPESAS!$H:$H, DESPESAS!$F:$F, "Carnê de arrecadação - MEI", DESPESAS!$N:$N, 11, DESPESAS!$O:$O, $E$5, DESPESAS!$J:$J, "Paga") | O23: =SUMIFS(DESPESAS!$H:$H, DESPESAS!$F:$F, "Carnê de arrecadação - MEI", DESPESAS!$N:$N, 12, DESPESAS!$O:$O, $E$5, DESPESAS!$J:$J, "Paga") | P23: =SUM(D23:O23)
B24: 2.5 | C24: DAS - Documento de Arrecadação Simples | D24: =SUMIFS(DESPESAS!$H:$H, DESPESAS!$F:$F, "DAS - Documento de Arrecadação Simples", DESPESAS!$N:$N, 1, DESPESAS!$O:$O, $E$5, DESPESAS!$J:$J, "Paga") | E24: =SUMIFS(DESPESAS!$H:$H, DESPESAS!$F:$F, "DAS - Documento de Arrecadação Simples", DESPESAS!$N:$N, 2, DESPESAS!$O:$O, $E$5, DESPESAS!$J:$J, "Paga") | F24: =SUMIFS(DESPESAS!$H:$H, DESPESAS!$F:$F, "DAS - Documento de Arrecadação Simples", DESPESAS!$N:$N, 3, DESPESAS!$O:$O, $E$5, DESPESAS!$J:$J, "Paga") | G24: =SUMIFS(DESPESAS!$H:$H, DESPESAS!$F:$F, "DAS - Documento de Arrecadação Simples", DESPESAS!$N:$N, 4, DESPESAS!$O:$O, $E$5, DESPESAS!$J:$J, "Paga") | H24: =SUMIFS(DESPESAS!$H:$H, DESPESAS!$F:$F, "DAS - Documento de Arrecadação Simples", DESPESAS!$N:$N, 5, DESPESAS!$O:$O, $E$5, DESPESAS!$J:$J, "Paga") | I24: =SUMIFS(DESPESAS!$H:$H, DESPESAS!$F:$F, "DAS - Documento de Arrecadação Simples", DESPESAS!$N:$N, 6, DESPESAS!$O:$O, $E$5, DESPESAS!$J:$J, "Paga") | J24: =SUMIFS(DESPESAS!$H:$H, DESPESAS!$F:$F, "DAS - Documento de Arrecadação Simples", DESPESAS!$N:$N, 7, DESPESAS!$O:$O, $E$5, DESPESAS!$J:$J, "Paga") | K24: =SUMIFS(DESPESAS!$H:$H, DESPESAS!$F:$F, "DAS - Documento de Arrecadação Simples", DESPESAS!$N:$N, 8, DESPESAS!$O:$O, $E$5, DESPESAS!$J:$J, "Paga") | L24: =SUMIFS(DESPESAS!$H:$H, DESPESAS!$F:$F, "DAS - Documento de Arrecadação Simples", DESPESAS!$N:$N, 9, DESPESAS!$O:$O, $E$5, DESPESAS!$J:$J, "Paga") | M24: =SUMIFS(DESPESAS!$H:$H, DESPESAS!$F:$F, "DAS - Documento de Arrecadação Simples", DESPESAS!$N:$N, 10, DESPESAS!$O:$O, $E$5, DESPESAS!$J:$J, "Paga") | N24: =SUMIFS(DESPESAS!$H:$H, DESPESAS!$F:$F, "DAS - Documento de Arrecadação Simples", DESPESAS!$N:$N, 11, DESPESAS!$O:$O, $E$5, DESPESAS!$J:$J, "Paga") | O24: =SUMIFS(DESPESAS!$H:$H, DESPESAS!$F:$F, "DAS - Documento de Arrecadação Simples", DESPESAS!$N:$N, 12, DESPESAS!$O:$O, $E$5, DESPESAS!$J:$J, "Paga") | P24: =SUM(D24:O24)
B25: 2.6 | C25: Folha de pagamento | D25: 0 | E25: =SUMIFS(DESPESAS!$H:$H, DESPESAS!$F:$F, "Folha de pagamento", DESPESAS!$N:$N, 2, DESPESAS!$O:$O, $E$5, DESPESAS!$J:$J, "Paga") | F25: =SUMIFS(DESPESAS!$H:$H, DESPESAS!$F:$F, "Folha de pagamento", DESPESAS!$N:$N, 3, DESPESAS!$O:$O, $E$5, DESPESAS!$J:$J, "Paga") | G25: =SUMIFS(DESPESAS!$H:$H, DESPESAS!$F:$F, "Folha de pagamento", DESPESAS!$N:$N, 4, DESPESAS!$O:$O, $E$5, DESPESAS!$J:$J, "Paga") | H25: =SUMIFS(DESPESAS!$H:$H, DESPESAS!$F:$F, "Folha de pagamento", DESPESAS!$N:$N, 5, DESPESAS!$O:$O, $E$5, DESPESAS!$J:$J, "Paga") | I25: =SUMIFS(DESPESAS!$H:$H, DESPESAS!$F:$F, "Folha de pagamento", DESPESAS!$N:$N, 6, DESPESAS!$O:$O, $E$5, DESPESAS!$J:$J, "Paga") | J25: =SUMIFS(DESPESAS!$H:$H, DESPESAS!$F:$F, "Folha de pagamento", DESPESAS!$N:$N, 7, DESPESAS!$O:$O, $E$5, DESPESAS!$J:$J, "Paga") | K25: =SUMIFS(DESPESAS!$H:$H, DESPESAS!$F:$F, "Folha de pagamento", DESPESAS!$N:$N, 8, DESPESAS!$O:$O, $E$5, DESPESAS!$J:$J, "Paga") | L25: =SUMIFS(DESPESAS!$H:$H, DESPESAS!$F:$F, "Folha de pagamento", DESPESAS!$N:$N, 9, DESPESAS!$O:$O, $E$5, DESPESAS!$J:$J, "Paga") | M25: =SUMIFS(DESPESAS!$H:$H, DESPESAS!$F:$F, "Folha de pagamento", DESPESAS!$N:$N, 10, DESPESAS!$O:$O, $E$5, DESPESAS!$J:$J, "Paga") | N25: =SUMIFS(DESPESAS!$H:$H, DESPESAS!$F:$F, "Folha de pagamento", DESPESAS!$N:$N, 11, DESPESAS!$O:$O, $E$5, DESPESAS!$J:$J, "Paga") | O25: =SUMIFS(DESPESAS!$H:$H, DESPESAS!$F:$F, "Folha de pagamento", DESPESAS!$N:$N, 12, DESPESAS!$O:$O, $E$5, DESPESAS!$J:$J, "Paga") | P25: =SUM(D25:O25)
B26: 2.7 | C26: Outros tributos (impostos, taxas, etc.) | D26: 0 | E26: =SUMIFS(DESPESAS!$H:$H, DESPESAS!$F:$F, "Outros tributos (impostos, taxas, etc.)", DESPESAS!$N:$N, 2, DESPESAS!$O:$O, $E$5, DESPESAS!$J:$J, "Paga") | F26: =SUMIFS(DESPESAS!$H:$H, DESPESAS!$F:$F, "Outros tributos (impostos, taxas, etc.)", DESPESAS!$N:$N, 3, DESPESAS!$O:$O, $E$5, DESPESAS!$J:$J, "Paga") | G26: =SUMIFS(DESPESAS!$H:$H, DESPESAS!$F:$F, "Outros tributos (impostos, taxas, etc.)", DESPESAS!$N:$N, 4, DESPESAS!$O:$O, $E$5, DESPESAS!$J:$J, "Paga") | H26: =SUMIFS(DESPESAS!$H:$H, DESPESAS!$F:$F, "Outros tributos (impostos, taxas, etc.)", DESPESAS!$N:$N, 5, DESPESAS!$O:$O, $E$5, DESPESAS!$J:$J, "Paga") | I26: =SUMIFS(DESPESAS!$H:$H, DESPESAS!$F:$F, "Outros tributos (impostos, taxas, etc.)", DESPESAS!$N:$N, 6, DESPESAS!$O:$O, $E$5, DESPESAS!$J:$J, "Paga") | J26: =SUMIFS(DESPESAS!$H:$H, DESPESAS!$F:$F, "Outros tributos (impostos, taxas, etc.)", DESPESAS!$N:$N, 7, DESPESAS!$O:$O, $E$5, DESPESAS!$J:$J, "Paga") | K26: =SUMIFS(DESPESAS!$H:$H, DESPESAS!$F:$F, "Outros tributos (impostos, taxas, etc.)", DESPESAS!$N:$N, 8, DESPESAS!$O:$O, $E$5, DESPESAS!$J:$J, "Paga") | L26: =SUMIFS(DESPESAS!$H:$H, DESPESAS!$F:$F, "Outros tributos (impostos, taxas, etc.)", DESPESAS!$N:$N, 9, DESPESAS!$O:$O, $E$5, DESPESAS!$J:$J, "Paga") | M26: =SUMIFS(DESPESAS!$H:$H, DESPESAS!$F:$F, "Outros tributos (impostos, taxas, etc.)", DESPESAS!$N:$N, 10, DESPESAS!$O:$O, $E$5, DESPESAS!$J:$J, "Paga") | N26: =SUMIFS(DESPESAS!$H:$H, DESPESAS!$F:$F, "Outros tributos (impostos, taxas, etc.)", DESPESAS!$N:$N, 11, DESPESAS!$O:$O, $E$5, DESPESAS!$J:$J, "Paga") | O26: =SUMIFS(DESPESAS!$H:$H, DESPESAS!$F:$F, "Outros tributos (impostos, taxas, etc.)", DESPESAS!$N:$N, 12, DESPESAS!$O:$O, $E$5, DESPESAS!$J:$J, "Paga") | P26: =SUM(D26:O26)
B27: 2.8 | C27: Gastos com juros e taxas bancos | D27: =0+SUMIFS(DESPESAS!$H:$H,DESPESAS!$F:$F,"Gastos com juros e taxas bancos",DESPESAS!$N:$N,1,DESPESAS!$O:$O,$E$5,DESPESAS!$J:$J,"Paga") | E27: =0+SUMIFS(DESPESAS!$H:$H,DESPESAS!$F:$F,"Gastos com juros e taxas bancos",DESPESAS!$N:$N,2,DESPESAS!$O:$O,$E$5,DESPESAS!$J:$J,"Paga") | F27: =0+SUMIFS(DESPESAS!$H:$H,DESPESAS!$F:$F,"Gastos com juros e taxas bancos",DESPESAS!$N:$N,3,DESPESAS!$O:$O,$E$5,DESPESAS!$J:$J,"Paga") | G27: =0+SUMIFS(DESPESAS!$H:$H,DESPESAS!$F:$F,"Gastos com juros e taxas bancos",DESPESAS!$N:$N,4,DESPESAS!$O:$O,$E$5,DESPESAS!$J:$J,"Paga") | H27: =0+SUMIFS(DESPESAS!$H:$H,DESPESAS!$F:$F,"Gastos com juros e taxas bancos",DESPESAS!$N:$N,5,DESPESAS!$O:$O,$E$5,DESPESAS!$J:$J,"Paga") | I27: =0+SUMIFS(DESPESAS!$H:$H,DESPESAS!$F:$F,"Gastos com juros e taxas bancos",DESPESAS!$N:$N,6,DESPESAS!$O:$O,$E$5,DESPESAS!$J:$J,"Paga") | J27: =0+SUMIFS(DESPESAS!$H:$H,DESPESAS!$F:$F,"Gastos com juros e taxas bancos",DESPESAS!$N:$N,7,DESPESAS!$O:$O,$E$5,DESPESAS!$J:$J,"Paga") | K27: =0+SUMIFS(DESPESAS!$H:$H,DESPESAS!$F:$F,"Gastos com juros e taxas bancos",DESPESAS!$N:$N,8,DESPESAS!$O:$O,$E$5,DESPESAS!$J:$J,"Paga") | L27: =0+SUMIFS(DESPESAS!$H:$H,DESPESAS!$F:$F,"Gastos com juros e taxas bancos",DESPESAS!$N:$N,9,DESPESAS!$O:$O,$E$5,DESPESAS!$J:$J,"Paga") | M27: =146.19+SUMIFS(DESPESAS!$H:$H,DESPESAS!$F:$F,"Gastos com juros e taxas bancos",DESPESAS!$N:$N,10,DESPESAS!$O:$O,$E$5,DESPESAS!$J:$J,"Paga") | N27: =0+SUMIFS(DESPESAS!$H:$H,DESPESAS!$F:$F,"Gastos com juros e taxas bancos",DESPESAS!$N:$N,11,DESPESAS!$O:$O,$E$5,DESPESAS!$J:$J,"Paga") | O27: =0+SUMIFS(DESPESAS!$H:$H,DESPESAS!$F:$F,"Gastos com juros e taxas bancos",DESPESAS!$N:$N,12,DESPESAS!$O:$O,$E$5,DESPESAS!$J:$J,"Paga") | P27: =SUM(D27:O27)
B28: 2.9 | C28: Aluguel da empresa | D28: =SUMIFS(DESPESAS!$H:$H, DESPESAS!$F:$F, "Aluguel da empresa", DESPESAS!$N:$N, 1, DESPESAS!$O:$O, $E$5, DESPESAS!$J:$J, "Paga") | E28: =SUMIFS(DESPESAS!$H:$H, DESPESAS!$F:$F, "Aluguel da empresa", DESPESAS!$N:$N, 2, DESPESAS!$O:$O, $E$5, DESPESAS!$J:$J, "Paga") | F28: =SUMIFS(DESPESAS!$H:$H, DESPESAS!$F:$F, "Aluguel da empresa", DESPESAS!$N:$N, 3, DESPESAS!$O:$O, $E$5, DESPESAS!$J:$J, "Paga") | G28: =SUMIFS(DESPESAS!$H:$H, DESPESAS!$F:$F, "Aluguel da empresa", DESPESAS!$N:$N, 4, DESPESAS!$O:$O, $E$5, DESPESAS!$J:$J, "Paga") | H28: =SUMIFS(DESPESAS!$H:$H, DESPESAS!$F:$F, "Aluguel da empresa", DESPESAS!$N:$N, 5, DESPESAS!$O:$O, $E$5, DESPESAS!$J:$J, "Paga") | I28: =SUMIFS(DESPESAS!$H:$H, DESPESAS!$F:$F, "Aluguel da empresa", DESPESAS!$N:$N, 6, DESPESAS!$O:$O, $E$5, DESPESAS!$J:$J, "Paga") | J28: =SUMIFS(DESPESAS!$H:$H, DESPESAS!$F:$F, "Aluguel da empresa", DESPESAS!$N:$N, 7, DESPESAS!$O:$O, $E$5, DESPESAS!$J:$J, "Paga") | K28: =SUMIFS(DESPESAS!$H:$H, DESPESAS!$F:$F, "Aluguel da empresa", DESPESAS!$N:$N, 8, DESPESAS!$O:$O, $E$5, DESPESAS!$J:$J, "Paga") | L28: =SUMIFS(DESPESAS!$H:$H, DESPESAS!$F:$F, "Aluguel da empresa", DESPESAS!$N:$N, 9, DESPESAS!$O:$O, $E$5, DESPESAS!$J:$J, "Paga") | M28: =SUMIFS(DESPESAS!$H:$H, DESPESAS!$F:$F, "Aluguel da empresa", DESPESAS!$N:$N, 10, DESPESAS!$O:$O, $E$5, DESPESAS!$J:$J, "Paga") | N28: =SUMIFS(DESPESAS!$H:$H, DESPESAS!$F:$F, "Aluguel da empresa", DESPESAS!$N:$N, 11, DESPESAS!$O:$O, $E$5, DESPESAS!$J:$J, "Paga") | O28: =SUMIFS(DESPESAS!$H:$H, DESPESAS!$F:$F, "Aluguel da empresa", DESPESAS!$N:$N, 12, DESPESAS!$O:$O, $E$5, DESPESAS!$J:$J, "Paga") | P28: =SUM(D28:O28)
B29: 2.10 | C29: Energia elétrica da empresa | D29: =SUMIFS(DESPESAS!$H:$H, DESPESAS!$F:$F, "Energia elétrica da empresa", DESPESAS!$N:$N, 1, DESPESAS!$O:$O, $E$5, DESPESAS!$J:$J, "Paga") | E29: =SUMIFS(DESPESAS!$H:$H, DESPESAS!$F:$F, "Energia elétrica da empresa", DESPESAS!$N:$N, 2, DESPESAS!$O:$O, $E$5, DESPESAS!$J:$J, "Paga") | F29: =SUMIFS(DESPESAS!$H:$H, DESPESAS!$F:$F, "Energia elétrica da empresa", DESPESAS!$N:$N, 3, DESPESAS!$O:$O, $E$5, DESPESAS!$J:$J, "Paga") | G29: =SUMIFS(DESPESAS!$H:$H, DESPESAS!$F:$F, "Energia elétrica da empresa", DESPESAS!$N:$N, 4, DESPESAS!$O:$O, $E$5, DESPESAS!$J:$J, "Paga") | H29: =SUMIFS(DESPESAS!$H:$H, DESPESAS!$F:$F, "Energia elétrica da empresa", DESPESAS!$N:$N, 5, DESPESAS!$O:$O, $E$5, DESPESAS!$J:$J, "Paga") | I29: =SUMIFS(DESPESAS!$H:$H, DESPESAS!$F:$F, "Energia elétrica da empresa", DESPESAS!$N:$N, 6, DESPESAS!$O:$O, $E$5, DESPESAS!$J:$J, "Paga") | J29: =SUMIFS(DESPESAS!$H:$H, DESPESAS!$F:$F, "Energia elétrica da empresa", DESPESAS!$N:$N, 7, DESPESAS!$O:$O, $E$5, DESPESAS!$J:$J, "Paga") | K29: =SUMIFS(DESPESAS!$H:$H, DESPESAS!$F:$F, "Energia elétrica da empresa", DESPESAS!$N:$N, 8, DESPESAS!$O:$O, $E$5, DESPESAS!$J:$J, "Paga") | L29: =SUMIFS(DESPESAS!$H:$H, DESPESAS!$F:$F, "Energia elétrica da empresa", DESPESAS!$N:$N, 9, DESPESAS!$O:$O, $E$5, DESPESAS!$J:$J, "Paga") | M29: =SUMIFS(DESPESAS!$H:$H, DESPESAS!$F:$F, "Energia elétrica da empresa", DESPESAS!$N:$N, 10, DESPESAS!$O:$O, $E$5, DESPESAS!$J:$J, "Paga") | N29: =SUMIFS(DESPESAS!$H:$H, DESPESAS!$F:$F, "Energia elétrica da empresa", DESPESAS!$N:$N, 11, DESPESAS!$O:$O, $E$5, DESPESAS!$J:$J, "Paga") | O29: =SUMIFS(DESPESAS!$H:$H, DESPESAS!$F:$F, "Energia elétrica da empresa", DESPESAS!$N:$N, 12, DESPESAS!$O:$O, $E$5, DESPESAS!$J:$J, "Paga") | P29: =SUM(D29:O29)
B30: 2.11 | C30: Água da empresa | D30: =SUMIFS(DESPESAS!$H:$H, DESPESAS!$F:$F, "Água da empresa", DESPESAS!$N:$N, 1, DESPESAS!$O:$O, $E$5, DESPESAS!$J:$J, "Paga") | E30: =SUMIFS(DESPESAS!$H:$H, DESPESAS!$F:$F, "Água da empresa", DESPESAS!$N:$N, 2, DESPESAS!$O:$O, $E$5, DESPESAS!$J:$J, "Paga") | F30: =SUMIFS(DESPESAS!$H:$H, DESPESAS!$F:$F, "Água da empresa", DESPESAS!$N:$N, 3, DESPESAS!$O:$O, $E$5, DESPESAS!$J:$J, "Paga") | G30: =SUMIFS(DESPESAS!$H:$H, DESPESAS!$F:$F, "Água da empresa", DESPESAS!$N:$N, 4, DESPESAS!$O:$O, $E$5, DESPESAS!$J:$J, "Paga") | H30: =SUMIFS(DESPESAS!$H:$H, DESPESAS!$F:$F, "Água da empresa", DESPESAS!$N:$N, 5, DESPESAS!$O:$O, $E$5, DESPESAS!$J:$J, "Paga") | I30: =SUMIFS(DESPESAS!$H:$H, DESPESAS!$F:$F, "Água da empresa", DESPESAS!$N:$N, 6, DESPESAS!$O:$O, $E$5, DESPESAS!$J:$J, "Paga") | J30: =SUMIFS(DESPESAS!$H:$H, DESPESAS!$F:$F, "Água da empresa", DESPESAS!$N:$N, 7, DESPESAS!$O:$O, $E$5, DESPESAS!$J:$J, "Paga") | K30: =SUMIFS(DESPESAS!$H:$H, DESPESAS!$F:$F, "Água da empresa", DESPESAS!$N:$N, 8, DESPESAS!$O:$O, $E$5, DESPESAS!$J:$J, "Paga") | L30: =SUMIFS(DESPESAS!$H:$H, DESPESAS!$F:$F, "Água da empresa", DESPESAS!$N:$N, 9, DESPESAS!$O:$O, $E$5, DESPESAS!$J:$J, "Paga") | M30: =SUMIFS(DESPESAS!$H:$H, DESPESAS!$F:$F, "Água da empresa", DESPESAS!$N:$N, 10, DESPESAS!$O:$O, $E$5, DESPESAS!$J:$J, "Paga") | N30: =SUMIFS(DESPESAS!$H:$H, DESPESAS!$F:$F, "Água da empresa", DESPESAS!$N:$N, 11, DESPESAS!$O:$O, $E$5, DESPESAS!$J:$J, "Paga") | O30: =SUMIFS(DESPESAS!$H:$H, DESPESAS!$F:$F, "Água da empresa", DESPESAS!$N:$N, 12, DESPESAS!$O:$O, $E$5, DESPESAS!$J:$J, "Paga") | P30: =SUM(D30:O30)
B31: 2.12 | C31: Telefone da empresa | D31: =SUMIFS(DESPESAS!$H:$H, DESPESAS!$F:$F, "Telefone da empresa", DESPESAS!$N:$N, 1, DESPESAS!$O:$O, $E$5, DESPESAS!$J:$J, "Paga") | E31: =SUMIFS(DESPESAS!$H:$H, DESPESAS!$F:$F, "Telefone da empresa", DESPESAS!$N:$N, 2, DESPESAS!$O:$O, $E$5, DESPESAS!$J:$J, "Paga") | F31: =SUMIFS(DESPESAS!$H:$H, DESPESAS!$F:$F, "Telefone da empresa", DESPESAS!$N:$N, 3, DESPESAS!$O:$O, $E$5, DESPESAS!$J:$J, "Paga") | G31: =SUMIFS(DESPESAS!$H:$H, DESPESAS!$F:$F, "Telefone da empresa", DESPESAS!$N:$N, 4, DESPESAS!$O:$O, $E$5, DESPESAS!$J:$J, "Paga") | H31: =SUMIFS(DESPESAS!$H:$H, DESPESAS!$F:$F, "Telefone da empresa", DESPESAS!$N:$N, 5, DESPESAS!$O:$O, $E$5, DESPESAS!$J:$J, "Paga") | I31: =SUMIFS(DESPESAS!$H:$H, DESPESAS!$F:$F, "Telefone da empresa", DESPESAS!$N:$N, 6, DESPESAS!$O:$O, $E$5, DESPESAS!$J:$J, "Paga") | J31: =SUMIFS(DESPESAS!$H:$H, DESPESAS!$F:$F, "Telefone da empresa", DESPESAS!$N:$N, 7, DESPESAS!$O:$O, $E$5, DESPESAS!$J:$J, "Paga") | K31: =SUMIFS(DESPESAS!$H:$H, DESPESAS!$F:$F, "Telefone da empresa", DESPESAS!$N:$N, 8, DESPESAS!$O:$O, $E$5, DESPESAS!$J:$J, "Paga") | L31: =SUMIFS(DESPESAS!$H:$H, DESPESAS!$F:$F, "Telefone da empresa", DESPESAS!$N:$N, 9, DESPESAS!$O:$O, $E$5, DESPESAS!$J:$J, "Paga") | M31: =SUMIFS(DESPESAS!$H:$H, DESPESAS!$F:$F, "Telefone da empresa", DESPESAS!$N:$N, 10, DESPESAS!$O:$O, $E$5, DESPESAS!$J:$J, "Paga") | N31: =SUMIFS(DESPESAS!$H:$H, DESPESAS!$F:$F, "Telefone da empresa", DESPESAS!$N:$N, 11, DESPESAS!$O:$O, $E$5, DESPESAS!$J:$J, "Paga") | O31: =SUMIFS(DESPESAS!$H:$H, DESPESAS!$F:$F, "Telefone da empresa", DESPESAS!$N:$N, 12, DESPESAS!$O:$O, $E$5, DESPESAS!$J:$J, "Paga") | P31: =SUM(D31:O31)
B32: 2.13 | C32: Internet da empresa | D32: =SUMIFS(DESPESAS!$H:$H, DESPESAS!$F:$F, "Internet da empresa", DESPESAS!$N:$N, 1, DESPESAS!$O:$O, $E$5, DESPESAS!$J:$J, "Paga") | E32: =SUMIFS(DESPESAS!$H:$H, DESPESAS!$F:$F, "Internet da empresa", DESPESAS!$N:$N, 2, DESPESAS!$O:$O, $E$5, DESPESAS!$J:$J, "Paga") | F32: =SUMIFS(DESPESAS!$H:$H, DESPESAS!$F:$F, "Internet da empresa", DESPESAS!$N:$N, 3, DESPESAS!$O:$O, $E$5, DESPESAS!$J:$J, "Paga") | G32: =SUMIFS(DESPESAS!$H:$H, DESPESAS!$F:$F, "Internet da empresa", DESPESAS!$N:$N, 4, DESPESAS!$O:$O, $E$5, DESPESAS!$J:$J, "Paga") | H32: =SUMIFS(DESPESAS!$H:$H, DESPESAS!$F:$F, "Internet da empresa", DESPESAS!$N:$N, 5, DESPESAS!$O:$O, $E$5, DESPESAS!$J:$J, "Paga") | I32: =SUMIFS(DESPESAS!$H:$H, DESPESAS!$F:$F, "Internet da empresa", DESPESAS!$N:$N, 6, DESPESAS!$O:$O, $E$5, DESPESAS!$J:$J, "Paga") | J32: =SUMIFS(DESPESAS!$H:$H, DESPESAS!$F:$F, "Internet da empresa", DESPESAS!$N:$N, 7, DESPESAS!$O:$O, $E$5, DESPESAS!$J:$J, "Paga") | K32: =SUMIFS(DESPESAS!$H:$H, DESPESAS!$F:$F, "Internet da empresa", DESPESAS!$N:$N, 8, DESPESAS!$O:$O, $E$5, DESPESAS!$J:$J, "Paga") | L32: =SUMIFS(DESPESAS!$H:$H, DESPESAS!$F:$F, "Internet da empresa", DESPESAS!$N:$N, 9, DESPESAS!$O:$O, $E$5, DESPESAS!$J:$J, "Paga") | M32: =SUMIFS(DESPESAS!$H:$H, DESPESAS!$F:$F, "Internet da empresa", DESPESAS!$N:$N, 10, DESPESAS!$O:$O, $E$5, DESPESAS!$J:$J, "Paga") | N32: =SUMIFS(DESPESAS!$H:$H, DESPESAS!$F:$F, "Internet da empresa", DESPESAS!$N:$N, 11, DESPESAS!$O:$O, $E$5, DESPESAS!$J:$J, "Paga") | O32: =SUMIFS(DESPESAS!$H:$H, DESPESAS!$F:$F, "Internet da empresa", DESPESAS!$N:$N, 12, DESPESAS!$O:$O, $E$5, DESPESAS!$J:$J, "Paga") | P32: =SUM(D32:O32)
B33: 2.14 | C33: Combustível da empresa | D33: =SUMIFS(DESPESAS!$H:$H, DESPESAS!$F:$F, "Combustível da empresa", DESPESAS!$N:$N, 1, DESPESAS!$O:$O, $E$5, DESPESAS!$J:$J, "Paga") | E33: =SUMIFS(DESPESAS!$H:$H, DESPESAS!$F:$F, "Combustível da empresa", DESPESAS!$N:$N, 2, DESPESAS!$O:$O, $E$5, DESPESAS!$J:$J, "Paga") | F33: =SUMIFS(DESPESAS!$H:$H, DESPESAS!$F:$F, "Combustível da empresa", DESPESAS!$N:$N, 3, DESPESAS!$O:$O, $E$5, DESPESAS!$J:$J, "Paga") | G33: =SUMIFS(DESPESAS!$H:$H, DESPESAS!$F:$F, "Combustível da empresa", DESPESAS!$N:$N, 4, DESPESAS!$O:$O, $E$5, DESPESAS!$J:$J, "Paga") | H33: =SUMIFS(DESPESAS!$H:$H, DESPESAS!$F:$F, "Combustível da empresa", DESPESAS!$N:$N, 5, DESPESAS!$O:$O, $E$5, DESPESAS!$J:$J, "Paga") | I33: =SUMIFS(DESPESAS!$H:$H, DESPESAS!$F:$F, "Combustível da empresa", DESPESAS!$N:$N, 6, DESPESAS!$O:$O, $E$5, DESPESAS!$J:$J, "Paga") | J33: =SUMIFS(DESPESAS!$H:$H, DESPESAS!$F:$F, "Combustível da empresa", DESPESAS!$N:$N, 7, DESPESAS!$O:$O, $E$5, DESPESAS!$J:$J, "Paga") | K33: =SUMIFS(DESPESAS!$H:$H, DESPESAS!$F:$F, "Combustível da empresa", DESPESAS!$N:$N, 8, DESPESAS!$O:$O, $E$5, DESPESAS!$J:$J, "Paga") | L33: =SUMIFS(DESPESAS!$H:$H, DESPESAS!$F:$F, "Combustível da empresa", DESPESAS!$N:$N, 9, DESPESAS!$O:$O, $E$5, DESPESAS!$J:$J, "Paga") | M33: =SUMIFS(DESPESAS!$H:$H, DESPESAS!$F:$F, "Combustível da empresa", DESPESAS!$N:$N, 10, DESPESAS!$O:$O, $E$5, DESPESAS!$J:$J, "Paga") | N33: =SUMIFS(DESPESAS!$H:$H, DESPESAS!$F:$F, "Combustível da empresa", DESPESAS!$N:$N, 11, DESPESAS!$O:$O, $E$5, DESPESAS!$J:$J, "Paga") | O33: =SUMIFS(DESPESAS!$H:$H, DESPESAS!$F:$F, "Combustível da empresa", DESPESAS!$N:$N, 12, DESPESAS!$O:$O, $E$5, DESPESAS!$J:$J, "Paga") | P33: =SUM(D33:O33)
B34: 2.15 | C34: Manutenção do veículo da empresa | D34: =SUMIFS(DESPESAS!$H:$H, DESPESAS!$F:$F, "Manutenção do veículo da empresa", DESPESAS!$N:$N, 1, DESPESAS!$O:$O, $E$5, DESPESAS!$J:$J, "Paga") | E34: =SUMIFS(DESPESAS!$H:$H, DESPESAS!$F:$F, "Manutenção do veículo da empresa", DESPESAS!$N:$N, 2, DESPESAS!$O:$O, $E$5, DESPESAS!$J:$J, "Paga") | F34: =SUMIFS(DESPESAS!$H:$H, DESPESAS!$F:$F, "Manutenção do veículo da empresa", DESPESAS!$N:$N, 3, DESPESAS!$O:$O, $E$5, DESPESAS!$J:$J, "Paga") | G34: =SUMIFS(DESPESAS!$H:$H, DESPESAS!$F:$F, "Manutenção do veículo da empresa", DESPESAS!$N:$N, 4, DESPESAS!$O:$O, $E$5, DESPESAS!$J:$J, "Paga") | H34: =SUMIFS(DESPESAS!$H:$H, DESPESAS!$F:$F, "Manutenção do veículo da empresa", DESPESAS!$N:$N, 5, DESPESAS!$O:$O, $E$5, DESPESAS!$J:$J, "Paga") | I34: =SUMIFS(DESPESAS!$H:$H, DESPESAS!$F:$F, "Manutenção do veículo da empresa", DESPESAS!$N:$N, 6, DESPESAS!$O:$O, $E$5, DESPESAS!$J:$J, "Paga") | J34: =SUMIFS(DESPESAS!$H:$H, DESPESAS!$F:$F, "Manutenção do veículo da empresa", DESPESAS!$N:$N, 7, DESPESAS!$O:$O, $E$5, DESPESAS!$J:$J, "Paga") | K34: =SUMIFS(DESPESAS!$H:$H, DESPESAS!$F:$F, "Manutenção do veículo da empresa", DESPESAS!$N:$N, 8, DESPESAS!$O:$O, $E$5, DESPESAS!$J:$J, "Paga") | L34: =SUMIFS(DESPESAS!$H:$H, DESPESAS!$F:$F, "Manutenção do veículo da empresa", DESPESAS!$N:$N, 9, DESPESAS!$O:$O, $E$5, DESPESAS!$J:$J, "Paga") | M34: =SUMIFS(DESPESAS!$H:$H, DESPESAS!$F:$F, "Manutenção do veículo da empresa", DESPESAS!$N:$N, 10, DESPESAS!$O:$O, $E$5, DESPESAS!$J:$J, "Paga") | N34: =SUMIFS(DESPESAS!$H:$H, DESPESAS!$F:$F, "Manutenção do veículo da empresa", DESPESAS!$N:$N, 11, DESPESAS!$O:$O, $E$5, DESPESAS!$J:$J, "Paga") | O34: =SUMIFS(DESPESAS!$H:$H, DESPESAS!$F:$F, "Manutenção do veículo da empresa", DESPESAS!$N:$N, 12, DESPESAS!$O:$O, $E$5, DESPESAS!$J:$J, "Paga") | P34: =SUM(D34:O34)
B35: 2.16 | C35: Manutenção da empresa | D35: =SUMIFS(DESPESAS!$H:$H, DESPESAS!$F:$F, "Manutenção da empresa", DESPESAS!$N:$N, 1, DESPESAS!$O:$O, $E$5, DESPESAS!$J:$J, "Paga") | E35: =SUMIFS(DESPESAS!$H:$H, DESPESAS!$F:$F, "Manutenção da empresa", DESPESAS!$N:$N, 2, DESPESAS!$O:$O, $E$5, DESPESAS!$J:$J, "Paga") | F35: =SUMIFS(DESPESAS!$H:$H, DESPESAS!$F:$F, "Manutenção da empresa", DESPESAS!$N:$N, 3, DESPESAS!$O:$O, $E$5, DESPESAS!$J:$J, "Paga") | G35: =SUMIFS(DESPESAS!$H:$H, DESPESAS!$F:$F, "Manutenção da empresa", DESPESAS!$N:$N, 4, DESPESAS!$O:$O, $E$5, DESPESAS!$J:$J, "Paga") | H35: =SUMIFS(DESPESAS!$H:$H, DESPESAS!$F:$F, "Manutenção da empresa", DESPESAS!$N:$N, 5, DESPESAS!$O:$O, $E$5, DESPESAS!$J:$J, "Paga") | I35: =SUMIFS(DESPESAS!$H:$H, DESPESAS!$F:$F, "Manutenção da empresa", DESPESAS!$N:$N, 6, DESPESAS!$O:$O, $E$5, DESPESAS!$J:$J, "Paga") | J35: =SUMIFS(DESPESAS!$H:$H, DESPESAS!$F:$F, "Manutenção da empresa", DESPESAS!$N:$N, 7, DESPESAS!$O:$O, $E$5, DESPESAS!$J:$J, "Paga") | K35: =SUMIFS(DESPESAS!$H:$H, DESPESAS!$F:$F, "Manutenção da empresa", DESPESAS!$N:$N, 8, DESPESAS!$O:$O, $E$5, DESPESAS!$J:$J, "Paga") | L35: =SUMIFS(DESPESAS!$H:$H, DESPESAS!$F:$F, "Manutenção da empresa", DESPESAS!$N:$N, 9, DESPESAS!$O:$O, $E$5, DESPESAS!$J:$J, "Paga") | M35: =SUMIFS(DESPESAS!$H:$H, DESPESAS!$F:$F, "Manutenção da empresa", DESPESAS!$N:$N, 10, DESPESAS!$O:$O, $E$5, DESPESAS!$J:$J, "Paga") | N35: =SUMIFS(DESPESAS!$H:$H, DESPESAS!$F:$F, "Manutenção da empresa", DESPESAS!$N:$N, 11, DESPESAS!$O:$O, $E$5, DESPESAS!$J:$J, "Paga") | O35: =SUMIFS(DESPESAS!$H:$H, DESPESAS!$F:$F, "Manutenção da empresa", DESPESAS!$N:$N, 12, DESPESAS!$O:$O, $E$5, DESPESAS!$J:$J, "Paga") | P35: =SUM(D35:O35)
B36: 2.17 | C36: Serviços contábeis | D36: =SUMIFS(DESPESAS!$H:$H, DESPESAS!$F:$F, "Serviços contábeis", DESPESAS!$N:$N, 1, DESPESAS!$O:$O, $E$5, DESPESAS!$J:$J, "Paga") | E36: =SUMIFS(DESPESAS!$H:$H, DESPESAS!$F:$F, "Serviços contábeis", DESPESAS!$N:$N, 2, DESPESAS!$O:$O, $E$5, DESPESAS!$J:$J, "Paga") | F36: =SUMIFS(DESPESAS!$H:$H, DESPESAS!$F:$F, "Serviços contábeis", DESPESAS!$N:$N, 3, DESPESAS!$O:$O, $E$5, DESPESAS!$J:$J, "Paga") | G36: =SUMIFS(DESPESAS!$H:$H, DESPESAS!$F:$F, "Serviços contábeis", DESPESAS!$N:$N, 4, DESPESAS!$O:$O, $E$5, DESPESAS!$J:$J, "Paga") | H36: =SUMIFS(DESPESAS!$H:$H, DESPESAS!$F:$F, "Serviços contábeis", DESPESAS!$N:$N, 5, DESPESAS!$O:$O, $E$5, DESPESAS!$J:$J, "Paga") | I36: =SUMIFS(DESPESAS!$H:$H, DESPESAS!$F:$F, "Serviços contábeis", DESPESAS!$N:$N, 6, DESPESAS!$O:$O, $E$5, DESPESAS!$J:$J, "Paga") | J36: =SUMIFS(DESPESAS!$H:$H, DESPESAS!$F:$F, "Serviços contábeis", DESPESAS!$N:$N, 7, DESPESAS!$O:$O, $E$5, DESPESAS!$J:$J, "Paga") | K36: =SUMIFS(DESPESAS!$H:$H, DESPESAS!$F:$F, "Serviços contábeis", DESPESAS!$N:$N, 8, DESPESAS!$O:$O, $E$5, DESPESAS!$J:$J, "Paga") | L36: =SUMIFS(DESPESAS!$H:$H, DESPESAS!$F:$F, "Serviços contábeis", DESPESAS!$N:$N, 9, DESPESAS!$O:$O, $E$5, DESPESAS!$J:$J, "Paga") | M36: =SUMIFS(DESPESAS!$H:$H, DESPESAS!$F:$F, "Serviços contábeis", DESPESAS!$N:$N, 10, DESPESAS!$O:$O, $E$5, DESPESAS!$J:$J, "Paga") | N36: =SUMIFS(DESPESAS!$H:$H, DESPESAS!$F:$F, "Serviços contábeis", DESPESAS!$N:$N, 11, DESPESAS!$O:$O, $E$5, DESPESAS!$J:$J, "Paga") | O36: =SUMIFS(DESPESAS!$H:$H, DESPESAS!$F:$F, "Serviços contábeis", DESPESAS!$N:$N, 12, DESPESAS!$O:$O, $E$5, DESPESAS!$J:$J, "Paga") | P36: =SUM(D36:O36)
B37: 2.18 | C37: Segurança da empresa | D37: =SUMIFS(DESPESAS!$H:$H, DESPESAS!$F:$F, "Segurança da empresa", DESPESAS!$N:$N, 1, DESPESAS!$O:$O, $E$5, DESPESAS!$J:$J, "Paga") | E37: =SUMIFS(DESPESAS!$H:$H, DESPESAS!$F:$F, "Segurança da empresa", DESPESAS!$N:$N, 2, DESPESAS!$O:$O, $E$5, DESPESAS!$J:$J, "Paga") | F37: =SUMIFS(DESPESAS!$H:$H, DESPESAS!$F:$F, "Segurança da empresa", DESPESAS!$N:$N, 3, DESPESAS!$O:$O, $E$5, DESPESAS!$J:$J, "Paga") | G37: =SUMIFS(DESPESAS!$H:$H, DESPESAS!$F:$F, "Segurança da empresa", DESPESAS!$N:$N, 4, DESPESAS!$O:$O, $E$5, DESPESAS!$J:$J, "Paga") | H37: =SUMIFS(DESPESAS!$H:$H, DESPESAS!$F:$F, "Segurança da empresa", DESPESAS!$N:$N, 5, DESPESAS!$O:$O, $E$5, DESPESAS!$J:$J, "Paga") | I37: =SUMIFS(DESPESAS!$H:$H, DESPESAS!$F:$F, "Segurança da empresa", DESPESAS!$N:$N, 6, DESPESAS!$O:$O, $E$5, DESPESAS!$J:$J, "Paga") | J37: =SUMIFS(DESPESAS!$H:$H, DESPESAS!$F:$F, "Segurança da empresa", DESPESAS!$N:$N, 7, DESPESAS!$O:$O, $E$5, DESPESAS!$J:$J, "Paga") | K37: =SUMIFS(DESPESAS!$H:$H, DESPESAS!$F:$F, "Segurança da empresa", DESPESAS!$N:$N, 8, DESPESAS!$O:$O, $E$5, DESPESAS!$J:$J, "Paga") | L37: =SUMIFS(DESPESAS!$H:$H, DESPESAS!$F:$F, "Segurança da empresa", DESPESAS!$N:$N, 9, DESPESAS!$O:$O, $E$5, DESPESAS!$J:$J, "Paga") | M37: =SUMIFS(DESPESAS!$H:$H, DESPESAS!$F:$F, "Segurança da empresa", DESPESAS!$N:$N, 10, DESPESAS!$O:$O, $E$5, DESPESAS!$J:$J, "Paga") | N37: =SUMIFS(DESPESAS!$H:$H, DESPESAS!$F:$F, "Segurança da empresa", DESPESAS!$N:$N, 11, DESPESAS!$O:$O, $E$5, DESPESAS!$J:$J, "Paga") | O37: =SUMIFS(DESPESAS!$H:$H, DESPESAS!$F:$F, "Segurança da empresa", DESPESAS!$N:$N, 12, DESPESAS!$O:$O, $E$5, DESPESAS!$J:$J, "Paga") | P37: =SUM(D37:O37)
B38: 2.19 | C38: Despesas diversas da empresa | D38: =SUMIFS(DESPESAS!$H:$H, DESPESAS!$F:$F, "Despesas diversas da empresa", DESPESAS!$N:$N, 1, DESPESAS!$O:$O, $E$5, DESPESAS!$J:$J, "Paga") | E38: =SUMIFS(DESPESAS!$H:$H, DESPESAS!$F:$F, "Despesas diversas da empresa", DESPESAS!$N:$N, 2, DESPESAS!$O:$O, $E$5, DESPESAS!$J:$J, "Paga") | F38: =SUMIFS(DESPESAS!$H:$H, DESPESAS!$F:$F, "Despesas diversas da empresa", DESPESAS!$N:$N, 3, DESPESAS!$O:$O, $E$5, DESPESAS!$J:$J, "Paga") | G38: =SUMIFS(DESPESAS!$H:$H, DESPESAS!$F:$F, "Despesas diversas da empresa", DESPESAS!$N:$N, 4, DESPESAS!$O:$O, $E$5, DESPESAS!$J:$J, "Paga") | H38: =SUMIFS(DESPESAS!$H:$H, DESPESAS!$F:$F, "Despesas diversas da empresa", DESPESAS!$N:$N, 5, DESPESAS!$O:$O, $E$5, DESPESAS!$J:$J, "Paga") | I38: =SUMIFS(DESPESAS!$H:$H, DESPESAS!$F:$F, "Despesas diversas da empresa", DESPESAS!$N:$N, 6, DESPESAS!$O:$O, $E$5, DESPESAS!$J:$J, "Paga") | J38: =SUMIFS(DESPESAS!$H:$H, DESPESAS!$F:$F, "Despesas diversas da empresa", DESPESAS!$N:$N, 7, DESPESAS!$O:$O, $E$5, DESPESAS!$J:$J, "Paga") | K38: =SUMIFS(DESPESAS!$H:$H, DESPESAS!$F:$F, "Despesas diversas da empresa", DESPESAS!$N:$N, 8, DESPESAS!$O:$O, $E$5, DESPESAS!$J:$J, "Paga") | L38: =SUMIFS(DESPESAS!$H:$H, DESPESAS!$F:$F, "Despesas diversas da empresa", DESPESAS!$N:$N, 9, DESPESAS!$O:$O, $E$5, DESPESAS!$J:$J, "Paga") | M38: =SUMIFS(DESPESAS!$H:$H, DESPESAS!$F:$F, "Despesas diversas da empresa", DESPESAS!$N:$N, 10, DESPESAS!$O:$O, $E$5, DESPESAS!$J:$J, "Paga") | N38: =SUMIFS(DESPESAS!$H:$H, DESPESAS!$F:$F, "Despesas diversas da empresa", DESPESAS!$N:$N, 11, DESPESAS!$O:$O, $E$5, DESPESAS!$J:$J, "Paga") | O38: =SUMIFS(DESPESAS!$H:$H, DESPESAS!$F:$F, "Despesas diversas da empresa", DESPESAS!$N:$N, 12, DESPESAS!$O:$O, $E$5, DESPESAS!$J:$J, "Paga") | P38: =SUM(D38:O38)
B39: 2 | C39: TOTAL DE SAÍDAS | D39: =SUM(D20:D38) | E39: =SUM(E20:E38) | F39: =SUM(F20:F38) | G39: =SUM(G20:G38) | H39: =SUM(H20:H38) | I39: =SUM(I20:I38) | J39: =SUM(J20:J38) | K39: =SUM(K20:K38) | ... P39: =SUM(P20:P38)
B41: 3 | C41: RESULTADO PERÍODO (SALDO OPERACIONAL CAIXA) | D41: =D17-D39 | E41: =E17-E39 | F41: =F17-F39 | G41: =G17-G39 | H41: =H17-H39 | I41: =I17-I39 | J41: =J17-J39 | K41: =K17-K39 | ... P41: =P17-P39
B42: 4 | C42: SALDO ACUMULADO DE CAIXA | D42: =D41 | E42: =D42+E41 | F42: =E42+F41 | G42: =F42+G41 | H42: =G42+H41 | I42: =H42+I41 | J42: =I42+J41 | K42: =J42+K41 | L42: =K42+L41 | ... O42: =N42+O41 | P42: =O42
B44: * Vendas e Prestação de Serviço sem Nota Fiscal: O MEI deverá obrigatoriamente emitir nota fiscal nas vendas e nas prestações de serviços realizadas para pessoas jurídicas (CNPJ), ficando dispensado para pessoa física (CPF).
B45: ** Retirada do(s) Proprietário(s): não limita-se somente à retirada de valores (pró-labore), mas também ao pagamento de despesas pessoais com dinheiro do caixa.
B46: *** Gastos com Serviços Prestados: englobam custos com ferramentas de trabalho, materiais e insumos utilizados diretamente na realização do serviço.

Sheet DESPESAS
A1: ID_DESPESA | B1: DATA_COMPETENCIA | C1: DATA_VENCIMENTO | D1: DATA_PAGAMENTO | E1: GRUPO_DRE | F1: CATEGORIA_FLUXO | G1: DESCRICAO_FAVORECIDO | H1: VALOR | I1: FORMA_PAGTO | J1: STATUS | K1: OPERADOR | L1: MES_COMP | M1: ANO_COMP | N1: MES_PAGTO | O1: ANO_PAGTO
A2: 1 | B2: 46296.125 | C2: 46300.125 | D2: 46300.125 | E2: 6.2 Despesas Administrativas | F2: Aluguel da empresa | G2: Imobiliária Central - Aluguel Out/2026 | H2: 280 | I2: PIX | J2: Paga | K2: Administrador | L2: 10 | M2: 2026 | N2: 10 | O2: 2026
A3: 2 | B3: 46296.125 | C3: 46305.125 | D3: 46314 | E3: 6.2 Despesas Administrativas | F3: Energia elétrica da empresa | G3: Cia de Energia - Conta Luz Outubro | H3: 185.4 | I3: Boleto | J3: Paga | K3: Administrador | L3: 10 | M3: 2026 | N3: 10 | O3: 2026
A4: 3 | B4: 46296.125 | C4: 46305.125 | D4: 46305.125 | E4: 6.2 Despesas Administrativas | F4: Água da empresa | G4: Saneamento Básico - Conta Água Outubro | H4: 74.9 | I4: PIX | J4: Paga | K4: Administrador | L4: 10 | M4: 2026 | N4: 10 | O4: 2026
A5: 4 | B5: 46296.125 | C5: 46307.125 | D5: 46307.125 | E5: 6.2 Despesas Administrativas | F5: Internet da empresa | G5: Fibra Telecom Empresarial 600MB | H5: 119.9 | I5: Débito Automático | J5: Paga | K5: Administrador | L5: 10 | M5: 2026 | N5: 10 | O5: 2026
A6: 5 | B6: 46300.125 | C6: 46315.125 | D6: 46310.125 | E6: 2.2 (-) Impostos e Contribuições sobre vendas | F6: DAS - Documento de Arrecadação Simples | G6: Guia DAS Simples Nacional Competência Out | H6: 145 | I6: PIX | J6: Paga | K6: Administrador | L6: 10 | M6: 2026 | N6: 10 | O6: 2026
A7: 6 | B7: 46305.125 | C7: 46310.125 | D7: 46310.125 | E7: 11.1 Serviços de contabilidade | F7: Serviços contábeis | G7: Honorários Escritório Contábil | H7: 250 | I7: Transferência | J7: Paga | K7: Administrador | L7: 10 | M7: 2026 | N7: 10 | O7: 2026
A8: 7 | B8: 46307.125 | C8: 46320.125 | D8: 46313 | E8: 11.3 Manutenção da empresa | F8: Manutenção da empresa | G8: Manutenção Ar-Condicionado Recepção | H8: 160 | I8: Boleto | J8: Paga | K8: Administrador | L8: 10 | M8: 2026 | N8: 10 | O8: 2026
A9: 8 | B9: 46310.125 | C9: 46325.125 | D9: 46314 | E9: 6.2 Despesas Administrativas | F9: Folha de pagamento | G9: Adiantamento Salarial Recepção | H9: 180 | I9: PIX | J9: Paga | K9: Administrador | L9: 10 | M9: 2026 | N9: 10 | O9: 2026

Sheet INVENTARIO
B2: 📦 GESTÃO DE ESTOQUE & INVENTÁRIO COMERCIAL (PRODUTOS & SERVIÇOS)
B5: 📦 TOTAL ITENS ESTOQUE | D5: 💵 CUSTO TOTAL ESTOQUE | F5: 💰 VALOR VENDA ESTOQUE | H5: 📈 LUCRO PROJETADO | J5: ⚠️ ESTOQUE BAIXO / ZERADO
B6: =SUM(H12:H1010) | D6: =SUM(K12:K1010) | F6: =SUM(L12:L1010) | H6: =SUM(M12:M1010) | J6: =COUNTIF(J12:J1010,"ZERADO")+COUNTIF(J12:J1010,"ESTOQUE BAIXO")
B11: ID | C11: Tipo | D11: Produto / Serviço | E11: Preço Custo | F11: Margem (%) | G11: Preço Final | H11: Estoque | I11: Mínimo | J11: Status | K11: Total Custo | L11: Total Venda | M11: Lucro Projetado
B12: 1 | C12: Produto | D12: Touca de natação adulto cinza tam. GG | E12: 20.32 | F12: 50 | G12: =ROUND(E12*(1+IF(ABS(F12)<=1,F12,F12/100)),2) | H12: 5 | I12: 5 | J12: =IF(OR(UPPER(C12)="SERVIÇO",UPPER(C12)="SERVICO"),"SERVIÇO",IF(H12<=0,"ZERADO",IF(H12<=I12,"ESTOQUE BAIXO","NORMAL"))) | K12: =IF(OR(UPPER(C12)="SERVIÇO",UPPER(C12)="SERVICO"),0,N(H12)*N(E12)) | L12: =IF(OR(UPPER(C12)="SERVIÇO",UPPER(C12)="SERVICO"),0,N(H12)*N(G12)) | M12: =IF(OR(UPPER(C12)="SERVIÇO",UPPER(C12)="SERVICO"),0,L12-K12)
B13: 2 | C13: Produto | D13: Bola de pilates ventilado azul | E13: 80.63 | F13: 200 | G13: =ROUND(E13*(1+IF(ABS(F13)<=1,F13,F13/100)),2) | H13: 15 | I13: 5 | J13: =IF(OR(UPPER(C13)="SERVIÇO",UPPER(C13)="SERVICO"),"SERVIÇO",IF(H13<=0,"ZERADO",IF(H13<=I13,"ESTOQUE BAIXO","NORMAL"))) | K13: =IF(OR(UPPER(C13)="SERVIÇO",UPPER(C13)="SERVICO"),0,N(H13)*N(E13)) | L13: =IF(OR(UPPER(C13)="SERVIÇO",UPPER(C13)="SERVICO"),0,N(H13)*N(G13)) | M13: =IF(OR(UPPER(C13)="SERVIÇO",UPPER(C13)="SERVICO"),0,L13-K13)
B14: 3 | C14: Produto | D14: Bola de vôlei profissional verde | E14: 43.47 | F14: 50 | G14: =ROUND(E14*(1+IF(ABS(F14)<=1,F14,F14/100)),2) | H14: 14 | I14: 5 | J14: =IF(OR(UPPER(C14)="SERVIÇO",UPPER(C14)="SERVICO"),"SERVIÇO",IF(H14<=0,"ZERADO",IF(H14<=I14,"ESTOQUE BAIXO","NORMAL"))) | K14: =IF(OR(UPPER(C14)="SERVIÇO",UPPER(C14)="SERVICO"),0,N(H14)*N(E14)) | L14: =IF(OR(UPPER(C14)="SERVIÇO",UPPER(C14)="SERVICO"),0,N(H14)*N(G14)) | M14: =IF(OR(UPPER(C14)="SERVIÇO",UPPER(C14)="SERVICO"),0,L14-K14)
B15: 4 | C15: Produto | D15: Saco de pancadas ventilado verde | E15: 592.51 | F15: 50 | G15: =ROUND(E15*(1+IF(ABS(F15)<=1,F15,F15/100)),2) | H15: 14 | I15: 5 | J15: =IF(OR(UPPER(C15)="SERVIÇO",UPPER(C15)="SERVICO"),"SERVIÇO",IF(H15<=0,"ZERADO",IF(H15<=I15,"ESTOQUE BAIXO","NORMAL"))) | K15: =IF(OR(UPPER(C15)="SERVIÇO",UPPER(C15)="SERVICO"),0,N(H15)*N(E15)) | L15: =IF(OR(UPPER(C15)="SERVIÇO",UPPER(C15)="SERVICO"),0,N(H15)*N(G15)) | M15: =IF(OR(UPPER(C15)="SERVIÇO",UPPER(C15)="SERVICO"),0,L15-K15)
B16: 5 | C16: Produto | D16: Skate alta performance verde | E16: 319.04 | F16: 50 | G16: =ROUND(E16*(1+IF(ABS(F16)<=1,F16,F16/100)),2) | H16: 15 | I16: 5 | J16: =IF(OR(UPPER(C16)="SERVIÇO",UPPER(C16)="SERVICO"),"SERVIÇO",IF(H16<=0,"ZERADO",IF(H16<=I16,"ESTOQUE BAIXO","NORMAL"))) | K16: =IF(OR(UPPER(C16)="SERVIÇO",UPPER(C16)="SERVICO"),0,N(H16)*N(E16)) | L16: =IF(OR(UPPER(C16)="SERVIÇO",UPPER(C16)="SERVICO"),0,N(H16)*N(G16)) | M16: =IF(OR(UPPER(C16)="SERVIÇO",UPPER(C16)="SERVICO"),0,L16-K16)
B17: 6 | C17: Produto | D17: Bolsa de academia leve laranja | E17: 80.98 | F17: 50 | G17: =ROUND(E17*(1+IF(ABS(F17)<=1,F17,F17/100)),2) | H17: 15 | I17: 5 | J17: =IF(OR(UPPER(C17)="SERVIÇO",UPPER(C17)="SERVICO"),"SERVIÇO",IF(H17<=0,"ZERADO",IF(H17<=I17,"ESTOQUE BAIXO","NORMAL"))) | K17: =IF(OR(UPPER(C17)="SERVIÇO",UPPER(C17)="SERVICO"),0,N(H17)*N(E17)) | L17: =IF(OR(UPPER(C17)="SERVIÇO",UPPER(C17)="SERVICO"),0,N(H17)*N(G17)) | M17: =IF(OR(UPPER(C17)="SERVIÇO",UPPER(C17)="SERVICO"),0,L17-K17)
B18: 7 | C18: Produto | D18: Chuteira society modelo básico azul tam. M | E18: 196.72 | F18: 50 | G18: =ROUND(E18*(1+IF(ABS(F18)<=1,F18,F18/100)),2) | H18: 15 | I18: 5 | J18: =IF(OR(UPPER(C18)="SERVIÇO",UPPER(C18)="SERVICO"),"SERVIÇO",IF(H18<=0,"ZERADO",IF(H18<=I18,"ESTOQUE BAIXO","NORMAL"))) | K18: =IF(OR(UPPER(C18)="SERVIÇO",UPPER(C18)="SERVICO"),0,N(H18)*N(E18)) | L18: =IF(OR(UPPER(C18)="SERVIÇO",UPPER(C18)="SERVICO"),0,N(H18)*N(G18)) | M18: =IF(OR(UPPER(C18)="SERVIÇO",UPPER(C18)="SERVICO"),0,L18-K18)
B19: 8 | C19: Produto | D19: Colchonete de exercício versão 2026 cinza | E19: 101.42 | F19: 50 | G19: =ROUND(E19*(1+IF(ABS(F19)<=1,F19,F19/100)),2) | H19: 14 | I19: 5 | J19: =IF(OR(UPPER(C19)="SERVIÇO",UPPER(C19)="SERVICO"),"SERVIÇO",IF(H19<=0,"ZERADO",IF(H19<=I19,"ESTOQUE BAIXO","NORMAL"))) | K19: =IF(OR(UPPER(C19)="SERVIÇO",UPPER(C19)="SERVICO"),0,N(H19)*N(E19)) | L19: =IF(OR(UPPER(C19)="SERVIÇO",UPPER(C19)="SERVICO"),0,N(H19)*N(G19)) | M19: =IF(OR(UPPER(C19)="SERVIÇO",UPPER(C19)="SERVICO"),0,L19-K19)
B20: 9 | C20: Produto | D20: Bastão de caminhada ventilado azul | E20: 175.91 | F20: 50 | G20: =ROUND(E20*(1+IF(ABS(F20)<=1,F20,F20/100)),2) | H20: 15 | I20: 5 | J20: =IF(OR(UPPER(C20)="SERVIÇO",UPPER(C20)="SERVICO"),"SERVIÇO",IF(H20<=0,"ZERADO",IF(H20<=I20,"ESTOQUE BAIXO","NORMAL"))) | K20: =IF(OR(UPPER(C20)="SERVIÇO",UPPER(C20)="SERVICO"),0,N(H20)*N(E20)) | L20: =IF(OR(UPPER(C20)="SERVIÇO",UPPER(C20)="SERVICO"),0,N(H20)*N(G20)) | M20: =IF(OR(UPPER(C20)="SERVIÇO",UPPER(C20)="SERVICO"),0,L20-K20)
B21: 10 | C21: Produto | D21: Bloco para yoga ventilado cinza | E21: 41.29 | F21: 50 | G21: =ROUND(E21*(1+IF(ABS(F21)<=1,F21,F21/100)),2) | H21: 15 | I21: 5 | J21: =IF(OR(UPPER(C21)="SERVIÇO",UPPER(C21)="SERVICO"),"SERVIÇO",IF(H21<=0,"ZERADO",IF(H21<=I21,"ESTOQUE BAIXO","NORMAL"))) | K21: =IF(OR(UPPER(C21)="SERVIÇO",UPPER(C21)="SERVICO"),0,N(H21)*N(E21)) | L21: =IF(OR(UPPER(C21)="SERVIÇO",UPPER(C21)="SERVICO"),0,N(H21)*N(G21)) | M21: =IF(OR(UPPER(C21)="SERVIÇO",UPPER(C21)="SERVICO"),0,L21-K21)
B22: 11 | C22: Produto | D22: Kimono de judô unissex verde tam. M | E22: 73.69 | F22: 50 | G22: =ROUND(E22*(1+IF(ABS(F22)<=1,F22,F22/100)),2) | H22: 15 | I22: 5 | J22: =IF(OR(UPPER(C22)="SERVIÇO",UPPER(C22)="SERVICO"),"SERVIÇO",IF(H22<=0,"ZERADO",IF(H22<=I22,"ESTOQUE BAIXO","NORMAL"))) | K22: =IF(OR(UPPER(C22)="SERVIÇO",UPPER(C22)="SERVICO"),0,N(H22)*N(E22)) | L22: =IF(OR(UPPER(C22)="SERVIÇO",UPPER(C22)="SERVICO"),0,N(H22)*N(G22)) | M22: =IF(OR(UPPER(C22)="SERVIÇO",UPPER(C22)="SERVICO"),0,L22-K22)
B23: 12 | C23: Produto | D23: Jaqueta esportiva profissional verde tam. M | E23: 147.45 | F23: 50 | G23: =ROUND(E23*(1+IF(ABS(F23)<=1,F23,F23/100)),2) | H23: 15 | I23: 5 | J23: =IF(OR(UPPER(C23)="SERVIÇO",UPPER(C23)="SERVICO"),"SERVIÇO",IF(H23<=0,"ZERADO",IF(H23<=I23,"ESTOQUE BAIXO","NORMAL"))) | K23: =IF(OR(UPPER(C23)="SERVIÇO",UPPER(C23)="SERVICO"),0,N(H23)*N(E23)) | L23: =IF(OR(UPPER(C23)="SERVIÇO",UPPER(C23)="SERVICO"),0,N(H23)*N(G23)) | M23: =IF(OR(UPPER(C23)="SERVIÇO",UPPER(C23)="SERVICO"),0,L23-K23)
... B1010: 999 | C1010: Produto | D1010: Bola de basquete modelo avançado vermelho | E1010: 64.52 | F1010: 50 | G1010: =ROUND(E1010*(1+IF(ABS(F1010)<=1,F1010,F1010/100)),2) | H1010: 15 | I1010: 5 | J1010: =IF(OR(UPPER(C1010)="SERVIÇO",UPPER(C1010)="SERVICO"),"SERVIÇO",IF(H1010<=0,"ZERADO",IF(H1010<=I1010,"ESTOQUE BAIXO","NORMAL"))) | K1010: =IF(OR(UPPER(C1010)="SERVIÇO",UPPER(C1010)="SERVICO"),0,N(H1010)*N(E1010)) | L1010: =IF(OR(UPPER(C1010)="SERVIÇO",UPPER(C1010)="SERVICO"),0,N(H1010)*N(G1010)) | M1010: =IF(OR(UPPER(C1010)="SERVIÇO",UPPER(C1010)="SERVICO"),0,L1010-K1010)

Sheet VENDAS
A1: ID_VENDA | B1: DATA_VENDA | C1: ID_CLIENTE | D1: NOME_CLIENTE | E1: TOTAL_BRUTO | F1: DESCONTO | G1: TOTAL_LIQUIDO | H1: FORMA_PAGTO | I1: STATUS | J1: PARCELAS | K1: TAXA_CARTAO | L1: VALOR_LIQUIDO_RECEBER | M1: OPERADOR
A2: 1 | B2: 46310 | C2: 4 | D2: Beatriz Souza Almeida | E2: 206.83 | F2: 0 | G2: 206.83 | H2: PIX | I2: Concluída | J2: 1x | K2: 0 | L2: 206.83 | M2: Vitória Karollyne
A3: 2 | B3: 46305.125 | C3: 1 | D3: Carlos Alberto da Silva | E3: 550 | F3: 50 | G3: 500 | H3: Cartão de Crédito | I3: Concluída | J3: 3x | K3: 0.035 | L3: 482.5 | M3: Vitória Karollyne
A4: 3 | B4: 46307.125 | C4: 2 | D4: Mariana Oliveira Santos | E4: 320 | F4: 0 | G4: 320 | H4: PIX | I4: Concluída | J4: 1x | K4: 0 | L4: 320 | M4: Geovana
A5: 4 | B5: 46308.125 | C5: 3 | D5: Ricardo Fernandes Souza | E5: 1200 | F5: 100 | G5: 1100 | H5: Cartão de Crédito | I5: Concluída | J5: 6x | K5: 0.045 | L5: 1050.5 | M5: Geovana
A6: 5 | B6: 46309.125 | C6: 5 | D6: Lucas Martins Pereira | E6: 180 | F6: 0 | G6: 180 | H6: Cartão de Débito | I6: Concluída | J6: 1x | K6: 0.015 | L6: 177.3 | M6: Administrador
A7: 6 | B7: 46310.125 | C7: 1 | D7: Carlos Alberto da Silva | E7: 450 | F7: 0 | G7: 450 | H7: Dinheiro | I7: Cancelada | J7: 1x | K7: 0 | L7: 450 | M7: Ana Silva
A8: 7 | B8: 46311 | C8: 6 | D8: vivaben | E8: 241.49 | F8: 0 | G8: 241.49 | H8: Cartão de Crédito | I8: Cancelada | J8: 1x | K8: 0.0089 | L8: 239.34 | M8: Vitória Karollyne Bezerra da Fonseca
A9: 8 | B9: 46311 | C9: 4 | D9: Beatriz Souza Almeida | E9: 542.5 | F9: 0 | G9: 542.5 | H9: Dinheiro | I9: Concluida | J9: 1x | K9: 0 | L9: 542.5 | M9: Administrador
A10: 9 | B10: 46314 | C10: 1 | D10: Carlos Alberto da Silva | E10: 2385.47 | F10: 200 | G10: 2185.47 | H10: Cartão de Crédito | I10: Concluida | J10: 1x | K10: 0.035 | L10: 2108.98 | M10: Administrador

Sheet ITENS_VENDA
A1: ID_ITEM | B1: ID_VENDA | C1: ID_PRODUTO | D1: DESCRICAO_PRODUTO | E1: PRECO_UNIT | F1: QUANTIDADE | G1: SUBTOTAL
A2: 1 | B2: 1 | C2: 2 | D2: Bola de pilates ventilado azul | E2: 134.38 | F2: 1 | G2: 134.38
A3: 2 | B3: 1 | C3: 3 | D3: Bola de vôlei profissional verde | E3: 72.45 | F3: 1 | G3: 72.45
A4: 2 | B4: 2 | C4: 1 | D4: Mouse Gamer RGB | E4: 150 | F4: 1 | G4: 150
A5: 3 | B5: 2 | C5: 2 | D5: Teclado Mecânico ABNT2 | E5: 350 | F5: 1 | G5: 350
A6: 4 | B6: 3 | C6: 3 | D6: Headset Surround 7.1 | E6: 320 | F6: 1 | G6: 320
A7: 5 | B7: 4 | C7: 4 | D7: Monitor 24 Pol IPS 144Hz | E7: 1100 | F7: 1 | G7: 1100
A8: 6 | B8: 5 | C8: 1 | D8: Mouse Gamer RGB | E8: 180 | F8: 1 | G8: 180
A9: 8 | B9: 7 | C9: 3 | D9: Bola de vôlei profissional verde | E9: 72.45 | F9: 1 | G9: 72.45
A10: 9 | B10: 7 | C10: 8 | D10: Colchonete de exercício versão 2026 cinza | E10: 169.04 | F10: 1 | G10: 169.04
A11: 10 | B11: 8 | C11: 1 | D11: Touca de natação adulto cinza tam. GG | E11: 54.25 | F11: 10 | G11: 542.5
A12: 11 | B12: 9 | C12: 996 | D12: Nadadeira modelo básico preto | E12: 49.89 | F12: 30 | G12: 1496.7
A13: 12 | B13: 9 | C13: 4 | D13: Saco de pancadas ventilado verde | E13: 888.77 | F13: 1 | G13: 888.77

Sheet PRODUTOS_SERVICOS
A1: ID | B1: TIPO | C1: DESCRICAO | D1: PRECO_CUSTO | E1: MARGEM_LUCRO | F1: PRECO_VENDA | G1: ESTOQUE_ATUAL | H1: ESTOQUE_MINIMO
A2: 1 | B2: Produto | C2: Touca de natação adulto cinza tam. GG | D2: 20.32 | E2: 50 | F2: =ROUND(D2*(1+(E2/100)),2) | G2: 5 | H2: 5
A3: 2 | B3: Produto | C3: Bola de pilates ventilado azul | D3: 80.63 | E3: 200 | F3: =ROUND(D3*(1+(E3/100)),2) | G3: 15 | H3: 5
A4: 3 | B4: Produto | C4: Bola de vôlei profissional verde | D4: 43.47 | E4: 50 | F4: =ROUND(D4*(1+(E4/100)),2) | G4: 14 | H4: 5
A5: 4 | B5: Produto | C5: Saco de pancadas ventilado verde | D5: 592.51 | E5: 50 | F5: =ROUND(D5*(1+(E5/100)),2) | G5: 14 | H5: 5
A6: 5 | B6: Produto | C6: Skate alta performance verde | D6: 319.04 | E6: 50 | F6: =ROUND(D6*(1+(E6/100)),2) | G6: 15 | H6: 5
A7: 6 | B7: Produto | C7: Bolsa de academia leve laranja | D7: 80.98 | E7: 50 | F7: =ROUND(D7*(1+(E7/100)),2) | G7: 15 | H7: 5
A8: 7 | B8: Produto | C8: Chuteira society modelo básico azul tam. M | D8: 196.72 | E8: 50 | F8: =ROUND(D8*(1+(E8/100)),2) | G8: 15 | H8: 5
A9: 8 | B9: Produto | C9: Colchonete de exercício versão 2026 cinza | D9: 101.42 | E9: 50 | F9: =ROUND(D9*(1+(E9/100)),2) | G9: 14 | H9: 5
A10: 9 | B10: Produto | C10: Bastão de caminhada ventilado azul | D10: 175.91 | E10: 50 | F10: =ROUND(D10*(1+(E10/100)),2) | G10: 15 | H10: 5
A11: 10 | B11: Produto | C11: Bloco para yoga ventilado cinza | D11: 41.29 | E11: 50 | F11: =ROUND(D11*(1+(E11/100)),2) | G11: 15 | H11: 5
A12: 11 | B12: Produto | C12: Kimono de judô unissex verde tam. M | D12: 73.69 | E12: 50 | F12: =ROUND(D12*(1+(E12/100)),2) | G12: 15 | H12: 5
A13: 12 | B13: Produto | C13: Jaqueta esportiva profissional verde tam. M | D13: 147.45 | E13: 50 | F13: =ROUND(D13*(1+(E13/100)),2) | G13: 15 | H13: 5
... A1000: 999 | B1000: Produto | C1000: Bola de basquete modelo avançado vermelho | D1000: 64.52 | E1000: 50 | F1000: =ROUND(D1000*(1+(E1000/100)),2) | G1000: 15 | H1000: 5

Sheet CLIENTES
A1: ID | B1: NOME | C1: CPF_CNPJ | D1: TELEFONE | E1: EMAIL | F1: ENDERECO | G1: BAIRRO | H1: DATA_NASCIMENTO | I1: IDADE
A2: 1 | B2: Carlos Alberto da Silva | C2: 123.456.789-00 | D2: (11) 98765-4321 | E2: carlos.silva@email.com | F2: Rua das Flores, 120 - SP | G2: Jardim das Flores | H2: 15/03/1985 | I2: 41
A3: 2 | B3: Mariana Oliveira Santos | C3: 234.567.890-11 | D3: (21) 99887-6655 | E3: mariana.santos@email.com | F3: Av. Brasil, 4500 - RJ | G3: Copacabana | H3: 22/07/1992 | I3: 34
A4: 3 | B4: Lucas Fernandes Souza | C4: 345.678.901-22 | D4: (31) 98452-1133 | E4: lucas.souza@email.com | F4: Rua Bahia, 88 - MG | G4: Savassi | H4: 32427 | I4: 37
A5: 4 | B5: Beatriz Souza Almeida | C5: 456.789.012-33 | D5: (41) 97123-9988 | E5: beatriz.almeida@email.com | F5: Rua XV de Novembro, 200 - PR | G5: Batel | H5: 34828 | I5: 31
A6: 6 | B6: vivaben | C6: 5823813120 | D6: 61982880812 | E6: sdASDDA!@gmail.com | F6: QND 27

Sheet USUARIOS
A1: 🔐 BASE DE ACESSO & CONTROLE DE OPERADORES (ADMINISTRATIVO)
A4: ID | B4: NOME | C4: USUARIO | D4: PIN_SENHA | E4: PERFIL | F4: ATIVO
A5: 1 | B5: Administrador | C5: admin | D5: 1234 | E5: ADMIN | F5: Sim
A6: 2 | B6: Vitória Karollyne Bezerra da Fonseca | C6: recepcao | D6: 1111 | E6: RECEPCAO | F6: Sim
A7: 3 | B7: Geovana | C7: recepcao | D7: 2222 | E7: RECEPCAO | F7: Sim
A8: 4 | B8: Maricélia | C8: Especialista | D8: tretapesada | E8: ESPECIALISTA | F8: Sim

Sheet CONFIG
A1: CAMPO | B1: VALOR
A2: RAZAO_SOCIAL | B2: MINHA EMPRESA DE VENDAS LTDA
A3: NOME_FANTASIA | B3: SISTEMA DE VENDAS & PDV
A4: CNPJ | B4: 12.345.678/0001-90
A5: TELEFONE | B5: (11) 98765-4321
A6: EMAIL | B6: contato@empresa.com.br
A7: ENDERECO | B7: Av. Paulista, 1000 - Bela Vista
A8: CIDADE_UF | B8: São Paulo - SP
A9: MENSAGEM_RODAPE | B9: Obrigado pela preferência! Volte sempre.
A10: LOGO_PATH | B10: logo_empresa.png
