Workbook

Sheet PDV_CAIXA
B2: 🛒 SISTEMA DE PONTO DE VENDA (PDV) - CAIXA ONLINE
B5: ⚡ Dica: Abra o menu superior 'SISTEMA PDV 🚀' para iniciar o Caixa ou buscar produtos rapidamente.
B7: 💰 VENDAS DO DIA | E7: 📦 ITENS VENDIDOS HOJE
B8: =SUMIFS(REGISTRO_VENDAS!G:G, REGISTRO_VENDAS!B:B, TODAY(), REGISTRO_VENDAS!I:I, "Concluida") | E8: =COUNTIFS(REGISTRO_VENDAS!B:B, TODAY(), REGISTRO_VENDAS!I:I, "Concluida")
B11: 📋 ÚLTIMAS TRANSAÇÕES REGISTRADAS NESTE CAIXA
B12: ID | C12: Hora/Data | D12: Cliente | E12: Forma Pagto | F12: Total Venda | G12: Status | H12: Operador
B13: =IF(REGISTRO_VENDAS!A2<>"", REGISTRO_VENDAS!A2, "") | C13: =IF(REGISTRO_VENDAS!B2<>"", REGISTRO_VENDAS!B2, "") | D13: =IF(REGISTRO_VENDAS!D2<>"", REGISTRO_VENDAS!D2, "") | E13: =IF(REGISTRO_VENDAS!H2<>"", REGISTRO_VENDAS!H2, "") | F13: =IF(REGISTRO_VENDAS!G2<>"", REGISTRO_VENDAS!G2, "") | G13: =IF(REGISTRO_VENDAS!I2<>"", REGISTRO_VENDAS!I2, "") | H13: =IF(REGISTRO_VENDAS!M2<>"", REGISTRO_VENDAS!M2, "")
B14: =IF(REGISTRO_VENDAS!A3<>"", REGISTRO_VENDAS!A3, "") | C14: =IF(REGISTRO_VENDAS!B3<>"", REGISTRO_VENDAS!B3, "") | D14: =IF(REGISTRO_VENDAS!D3<>"", REGISTRO_VENDAS!D3, "") | E14: =IF(REGISTRO_VENDAS!H3<>"", REGISTRO_VENDAS!H3, "") | F14: =IF(REGISTRO_VENDAS!G3<>"", REGISTRO_VENDAS!G3, "") | G14: =IF(REGISTRO_VENDAS!I3<>"", REGISTRO_VENDAS!I3, "") | H14: =IF(REGISTRO_VENDAS!M3<>"", REGISTRO_VENDAS!M3, "")
B15: =IF(REGISTRO_VENDAS!A4<>"", REGISTRO_VENDAS!A4, "") | C15: =IF(REGISTRO_VENDAS!B4<>"", REGISTRO_VENDAS!B4, "") | D15: =IF(REGISTRO_VENDAS!D4<>"", REGISTRO_VENDAS!D4, "") | E15: =IF(REGISTRO_VENDAS!H4<>"", REGISTRO_VENDAS!H4, "") | F15: =IF(REGISTRO_VENDAS!G4<>"", REGISTRO_VENDAS!G4, "") | G15: =IF(REGISTRO_VENDAS!I4<>"", REGISTRO_VENDAS!I4, "") | H15: =IF(REGISTRO_VENDAS!M4<>"", REGISTRO_VENDAS!M4, "")
B16: =IF(REGISTRO_VENDAS!A5<>"", REGISTRO_VENDAS!A5, "") | C16: =IF(REGISTRO_VENDAS!B5<>"", REGISTRO_VENDAS!B5, "") | D16: =IF(REGISTRO_VENDAS!D5<>"", REGISTRO_VENDAS!D5, "") | E16: =IF(REGISTRO_VENDAS!H5<>"", REGISTRO_VENDAS!H5, "") | F16: =IF(REGISTRO_VENDAS!G5<>"", REGISTRO_VENDAS!G5, "") | G16: =IF(REGISTRO_VENDAS!I5<>"", REGISTRO_VENDAS!I5, "") | H16: =IF(REGISTRO_VENDAS!M5<>"", REGISTRO_VENDAS!M5, "")
B17: =IF(REGISTRO_VENDAS!A6<>"", REGISTRO_VENDAS!A6, "") | C17: =IF(REGISTRO_VENDAS!B6<>"", REGISTRO_VENDAS!B6, "") | D17: =IF(REGISTRO_VENDAS!D6<>"", REGISTRO_VENDAS!D6, "") | E17: =IF(REGISTRO_VENDAS!H6<>"", REGISTRO_VENDAS!H6, "") | F17: =IF(REGISTRO_VENDAS!G6<>"", REGISTRO_VENDAS!G6, "") | G17: =IF(REGISTRO_VENDAS!I6<>"", REGISTRO_VENDAS!I6, "") | H17: =IF(REGISTRO_VENDAS!M6<>"", REGISTRO_VENDAS!M6, "")
B18: =IF(REGISTRO_VENDAS!A7<>"", REGISTRO_VENDAS!A7, "") | C18: =IF(REGISTRO_VENDAS!B7<>"", REGISTRO_VENDAS!B7, "") | D18: =IF(REGISTRO_VENDAS!D7<>"", REGISTRO_VENDAS!D7, "") | E18: =IF(REGISTRO_VENDAS!H7<>"", REGISTRO_VENDAS!H7, "") | F18: =IF(REGISTRO_VENDAS!G7<>"", REGISTRO_VENDAS!G7, "") | G18: =IF(REGISTRO_VENDAS!I7<>"", REGISTRO_VENDAS!I7, "") | H18: =IF(REGISTRO_VENDAS!M7<>"", REGISTRO_VENDAS!M7, "")
B19: =IF(REGISTRO_VENDAS!A8<>"", REGISTRO_VENDAS!A8, "") | C19: =IF(REGISTRO_VENDAS!B8<>"", REGISTRO_VENDAS!B8, "") | D19: =IF(REGISTRO_VENDAS!D8<>"", REGISTRO_VENDAS!D8, "") | E19: =IF(REGISTRO_VENDAS!H8<>"", REGISTRO_VENDAS!H8, "") | F19: =IF(REGISTRO_VENDAS!G8<>"", REGISTRO_VENDAS!G8, "") | G19: =IF(REGISTRO_VENDAS!I8<>"", REGISTRO_VENDAS!I8, "") | H19: =IF(REGISTRO_VENDAS!M8<>"", REGISTRO_VENDAS!M8, "")
B20: =IF(REGISTRO_VENDAS!A9<>"", REGISTRO_VENDAS!A9, "") | C20: =IF(REGISTRO_VENDAS!B9<>"", REGISTRO_VENDAS!B9, "") | D20: =IF(REGISTRO_VENDAS!D9<>"", REGISTRO_VENDAS!D9, "") | E20: =IF(REGISTRO_VENDAS!H9<>"", REGISTRO_VENDAS!H9, "") | F20: =IF(REGISTRO_VENDAS!G9<>"", REGISTRO_VENDAS!G9, "") | G20: =IF(REGISTRO_VENDAS!I9<>"", REGISTRO_VENDAS!I9, "") | H20: =IF(REGISTRO_VENDAS!M9<>"", REGISTRO_VENDAS!M9, "")
B21: =IF(REGISTRO_VENDAS!A10<>"", REGISTRO_VENDAS!A10, "") | C21: =IF(REGISTRO_VENDAS!B10<>"", REGISTRO_VENDAS!B10, "") | D21: =IF(REGISTRO_VENDAS!D10<>"", REGISTRO_VENDAS!D10, "") | E21: =IF(REGISTRO_VENDAS!H10<>"", REGISTRO_VENDAS!H10, "") | F21: =IF(REGISTRO_VENDAS!G10<>"", REGISTRO_VENDAS!G10, "") | G21: =IF(REGISTRO_VENDAS!I10<>"", REGISTRO_VENDAS!I10, "") | H21: =IF(REGISTRO_VENDAS!M10<>"", REGISTRO_VENDAS!M10, "")
B22: =IF(REGISTRO_VENDAS!A11<>"", REGISTRO_VENDAS!A11, "") | C22: =IF(REGISTRO_VENDAS!B11<>"", REGISTRO_VENDAS!B11, "") | D22: =IF(REGISTRO_VENDAS!D11<>"", REGISTRO_VENDAS!D11, "") | E22: =IF(REGISTRO_VENDAS!H11<>"", REGISTRO_VENDAS!H11, "") | F22: =IF(REGISTRO_VENDAS!G11<>"", REGISTRO_VENDAS!G11, "") | G22: =IF(REGISTRO_VENDAS!I11<>"", REGISTRO_VENDAS!I11, "") | H22: =IF(REGISTRO_VENDAS!M11<>"", REGISTRO_VENDAS!M11, "")
B23: =IF(REGISTRO_VENDAS!A12<>"", REGISTRO_VENDAS!A12, "") | C23: =IF(REGISTRO_VENDAS!B12<>"", REGISTRO_VENDAS!B12, "") | D23: =IF(REGISTRO_VENDAS!D12<>"", REGISTRO_VENDAS!D12, "") | E23: =IF(REGISTRO_VENDAS!H12<>"", REGISTRO_VENDAS!H12, "") | F23: =IF(REGISTRO_VENDAS!G12<>"", REGISTRO_VENDAS!G12, "") | G23: =IF(REGISTRO_VENDAS!I12<>"", REGISTRO_VENDAS!I12, "") | H23: =IF(REGISTRO_VENDAS!M12<>"", REGISTRO_VENDAS!M12, "")
B24: =IF(REGISTRO_VENDAS!A13<>"", REGISTRO_VENDAS!A13, "") | C24: =IF(REGISTRO_VENDAS!B13<>"", REGISTRO_VENDAS!B13, "") | D24: =IF(REGISTRO_VENDAS!D13<>"", REGISTRO_VENDAS!D13, "") | E24: =IF(REGISTRO_VENDAS!H13<>"", REGISTRO_VENDAS!H13, "") | F24: =IF(REGISTRO_VENDAS!G13<>"", REGISTRO_VENDAS!G13, "") | G24: =IF(REGISTRO_VENDAS!I13<>"", REGISTRO_VENDAS!I13, "") | H24: =IF(REGISTRO_VENDAS!M13<>"", REGISTRO_VENDAS!M13, "")
... B27: =IF(REGISTRO_VENDAS!A16<>"", REGISTRO_VENDAS!A16, "") | C27: =IF(REGISTRO_VENDAS!B16<>"", REGISTRO_VENDAS!B16, "") | D27: =IF(REGISTRO_VENDAS!D16<>"", REGISTRO_VENDAS!D16, "") | E27: =IF(REGISTRO_VENDAS!H16<>"", REGISTRO_VENDAS!H16, "") | F27: =IF(REGISTRO_VENDAS!G16<>"", REGISTRO_VENDAS!G16, "") | G27: =IF(REGISTRO_VENDAS!I16<>"", REGISTRO_VENDAS!I16, "") | H27: =IF(REGISTRO_VENDAS!M16<>"", REGISTRO_VENDAS!M16, "")

Sheet TABELA_PRECOS
A1: ID | B1: TIPO | C1: DESCRICAO | D1: PRECO_VENDA | E1: ESTOQUE_ATUAL
A2: 1 | B2: Produto | C2: Touca de natação adulto cinza tam. GG | D2: =ROUND(D2*(1+(E2/100)),2) | E2: 5
A3: 2 | B3: Produto | C3: Bola de pilates ventilado azul | D3: =ROUND(D3*(1+(E3/100)),2) | E3: 15
A4: 3 | B4: Produto | C4: Bola de vôlei profissional verde | D4: =ROUND(D4*(1+(E4/100)),2) | E4: 14
A5: 4 | B5: Produto | C5: Saco de pancadas ventilado verde | D5: =ROUND(D5*(1+(E5/100)),2) | E5: 14
A6: 5 | B6: Produto | C6: Skate alta performance verde | D6: =ROUND(D6*(1+(E6/100)),2) | E6: 15
A7: 6 | B7: Produto | C7: Bolsa de academia leve laranja | D7: =ROUND(D7*(1+(E7/100)),2) | E7: 15
A8: 7 | B8: Produto | C8: Chuteira society modelo básico azul tam. M | D8: =ROUND(D8*(1+(E8/100)),2) | E8: 15
A9: 8 | B9: Produto | C9: Colchonete de exercício versão 2026 cinza | D9: =ROUND(D9*(1+(E9/100)),2) | E9: 14
A10: 9 | B10: Produto | C10: Bastão de caminhada ventilado azul | D10: =ROUND(D10*(1+(E10/100)),2) | E10: 15
A11: 10 | B11: Produto | C11: Bloco para yoga ventilado cinza | D11: =ROUND(D11*(1+(E11/100)),2) | E11: 15
A12: 11 | B12: Produto | C12: Kimono de judô unissex verde tam. M | D12: =ROUND(D12*(1+(E12/100)),2) | E12: 15
A13: 12 | B13: Produto | C13: Jaqueta esportiva profissional verde tam. M | D13: =ROUND(D13*(1+(E13/100)),2) | E13: 15
... A1000: 999 | B1000: Produto | C1000: Bola de basquete modelo avançado vermelho | D1000: =ROUND(D1000*(1+(E1000/100)),2) | E1000: 15

Sheet CAD_CLIENTES
A1: ID | B1: NOME | C1: CPF_CNPJ | D1: TELEFONE | E1: EMAIL | F1: ENDERECO | G1: BAIRRO | H1: DATA_NASCIMENTO | I1: IDADE
A2: 1 | B2: Carlos Alberto da Silva | C2: 123.456.789-00 | D2: (11) 98765-4321 | E2: carlos.silva@email.com | F2: Rua das Flores, 120 - SP | G2: Jardim das Flores | H2: 15/03/1985 | I2: 41
A3: 2 | B3: Mariana Oliveira Santos | C3: 234.567.890-11 | D3: (21) 99887-6655 | E3: mariana.santos@email.com | F3: Av. Brasil, 4500 - RJ | G3: Copacabana | H3: 22/07/1992 | I3: 34
A4: 3 | B4: Lucas Fernandes Souza | C4: 345.678.901-22 | D4: (31) 98452-1133 | E4: lucas.souza@email.com | F4: Rua Bahia, 88 - MG | G4: Savassi | H4: 32427 | I4: 37
A5: 4 | B5: Beatriz Souza Almeida | C5: 456.789.012-33 | D5: (41) 97123-9988 | E5: beatriz.almeida@email.com | F5: Rua XV de Novembro, 200 - PR | G5: Batel | H5: 34828 | I5: 31
A6: 6 | B6: vivaben | C6: 5823813120 | D6: 61982880812 | E6: sdASDDA!@gmail.com | F6: QND 27

Sheet REGISTRO_VENDAS
A1: ID_VENDA | B1: DATA_VENDA | C1: ID_CLIENTE | D1: NOME_CLIENTE | E1: TOTAL_BRUTO | F1: DESCONTO | G1: TOTAL_LIQUIDO | H1: FORMA_PAGTO | I1: STATUS | J1: PARCELAS | K1: TAXA_CARTAO | L1: VALOR_LIQUIDO_RECEBER | M1: OPERADOR
A2: 1 | B2: 46310 | C2: 4 | D2: Beatriz Souza Almeida | E2: 206.83 | F2: 0 | G2: 206.83 | H2: PIX | I2: Concluída | J2: 1x | K2: 0 | L2: 206.83 | M2: Vitória Karollyne
A3: 2 | B3: 46305.125 | C3: 1 | D3: Carlos Alberto da Silva | E3: 550 | F3: 50 | G3: 500 | H3: Cartão de Crédito | I3: Concluída | J3: 3x | K3: 0.035 | L3: 482.5 | M3: Vitória Karollyne
A4: 3 | B4: 46307.125 | C4: 2 | D4: Mariana Oliveira Santos | E4: 320 | F4: 0 | G4: 320 | H4: PIX | I4: Concluída | J4: 1x | K4: 0 | L4: 320 | M4: Geovana
A5: 4 | B5: 46308.125 | C5: 3 | D5: Ricardo Fernandes Souza | E5: 1200 | F5: 100 | G5: 1100 | H5: Cartão de Crédito | I5: Concluída | J5: 6x | K5: 0.045 | L5: 1050.5 | M5: Geovana
A6: 5 | B6: 46309.125 | C6: 5 | D6: Lucas Martins Pereira | E6: 180 | F6: 0 | G6: 180 | H6: Cartão de Débito | I6: Concluída | J6: 1x | K6: 0.015 | L6: 177.3 | M6: Administrador
A7: 6 | B7: 46310.125 | C7: 1 | D7: Carlos Alberto da Silva | E7: 450 | F7: 0 | G7: 450 | H7: Dinheiro | I7: Cancelada | J7: 1x | K7: 0 | L7: 450 | M7: Ana Silva
A8: 7 | B8: 46311 | C8: 6 | D8: vivaben | E8: 241.49 | F8: 0 | G8: 241.49 | H8: Cartão de Crédito | I8: Cancelada | J8: 1x | K8: 0.0089 | L8: 239.34 | M8: Vitória Karollyne Bezerra da Fonseca
A9: 8 | B9: 46311 | C9: 4 | D9: Beatriz Souza Almeida | E9: 542.5 | F9: 0 | G9: 542.5 | H9: Dinheiro | I9: Concluida | J9: 1x | K9: 0 | L9: 542.5 | M9: Administrador
A10: 9 | B10: 46314 | C10: 1 | D10: Carlos Alberto da Silva | E10: 2385.47 | F10: 200 | G10: 2185.47 | H10: Cartão de Crédito | I10: Concluida | J10: 1x | K10: 0.035 | L10: 2108.98 | M10: Administrador
